[[{"key":"是否湖北居民","value":"否","type":"enum"},{"key":"患者编号","value":"0772000001","type":"string"},{"key":"患者名","value":"黄某","type":"string"},{"key":"省","value":"湖北省","type":"string"},{"key":"市","value":"武汉市","type":"string"},{"key":"区/县","value":"","type":"string"},{"key":"镇/街道","value":"","type":"string"},{"key":"年龄","value":49,"type":"int"},{"key":"性别","value":"男","type":"enum"},{"key":"密切患者","value":"","type":"string"},{"key":"离鄂时间","value":"2020-01-19T16:00:00.000Z","type":"date"},{"key":"离鄂城市","value":"武汉","type":"string"},{"key":"发病日期","value":"2020-01-20T16:00:00.000Z","type":"date"},{"key":"发病地点","value":"柳州市","type":"string"},{"key":"确诊日期","value":"2020-01-21T16:00:00.000Z","type":"date"},{"key":"确诊医院","value":"柳州市人民医院","type":"string"},{"key":"病症","value":"发热","type":"string"},{"key":"密触人数","value":"","type":"string"},{"key":"时间","value":"2020-01-19T16:00:00.000Z","type":"date"},{"key":"出行方式","value":"","type":"string"},{"key":"车次/车厢/座位","value":"","type":"string"},{"key":"起始（上车）地","value":"武汉","type":"string"},{"key":"目的（下车）地","value":"柳州","type":"string"},{"key":"地点","value":"","type":"string"},{"key":"事件","value":"","type":"string"},{"key":"开始时间","value":"","type":"date"},{"key":"结束时间","value":"","type":"date"},{"key":"数据源1","value":"http://app-h5.ngzb.com.cn/shareArticle?news_id=31777144&from=groupmessage&isappinstalled=0","type":"url"},{"key":"数据源2","value":"","type":"url"},{"key":"审核状态","value":"已审核","type":"enum"}],[{"key":"是否湖北居民","value":"否","type":"enum"},{"key":"患者编号","value":"0772000002","type":"string"},{"key":"患者名","value":"刘某","type":"string"},{"key":"省","value":"广东省","type":"string"},{"key":"市","value":"深圳市","type":"string"},{"key":"区/县","value":"","type":"string"},{"key":"镇/街道","value":"","type":"string"},{"key":"年龄","value":42,"type":"int"},{"key":"性别","value":"男","type":"enum"},{"key":"密切患者","value":"","type":"string"},{"key":"离鄂时间","value":"2020-01-14T16:00:00.000Z","type":"date"},{"key":"离鄂城市","value":"武汉","type":"string"},{"key":"发病日期","value":"2020-01-20T16:00:00.000Z","type":"date"},{"key":"发病地点","value":"柳州市","type":"string"},{"key":"确诊日期","value":"2020-01-23T16:00:00.000Z","type":"date"},{"key":"确诊医院","value":"柳州市人民医院","type":"string"},{"key":"病症","value":"","type":"string"},{"key":"密触人数","value":"","type":"string"},{"key":"时间","value":"2020-01-17T16:00:00.000Z","type":"date"},{"key":"出行方式","value":"","type":"string"},{"key":"车次/车厢/座位","value":"","type":"string"},{"key":"起始（上车）地","value":"深圳","type":"string"},{"key":"目的（下车）地","value":"柳州","type":"string"},{"key":"地点","value":"","type":"string"},{"key":"事件","value":"武汉出差","type":"string"},{"key":"开始时间","value":"2020-01-12T16:00:00.000Z","type":"date"},{"key":"结束时间","value":"2020-01-14T16:00:00.000Z","type":"date"},{"key":"数据源1","value":"http://app-h5.ngzb.com.cn/shareArticle?news_id=31777144&from=groupmessage&isappinstalled=0","type":"url"},{"key":"数据源2","value":"","type":"url"},{"key":"审核状态","value":"已审核","type":"enum"}],[{"key":"是否湖北居民","value":"是","type":"enum"},{"key":"患者编号","value":"0772000003","type":"string"},{"key":"患者名","value":"韩某","type":"string"},{"key":"省","value":"湖北省","type":"string"},{"key":"市","value":"武汉市","type":"string"},{"key":"区/县","value":"汉阳区","type":"string"},{"key":"镇/街道","value":"","type":"string"},{"key":"年龄","value":33,"type":"int"},{"key":"性别","value":"女","type":"enum"},{"key":"密切患者","value":"","type":"string"},{"key":"离鄂时间","value":"2020-01-17T16:00:00.000Z","type":"date"},{"key":"离鄂城市","value":"武汉","type":"string"},{"key":"发病日期","value":"2020-01-24T16:00:00.000Z","type":"date"},{"key":"发病地点","value":"柳州市","type":"string"},{"key":"确诊日期","value":"2020-01-25T16:00:00.000Z","type":"date"},{"key":"确诊医院","value":"柳州市人民医院","type":"string"},{"key":"病症","value":"发热","type":"string"},{"key":"密触人数","value":11,"type":"string"},{"key":"时间","value":"2020-01-17T16:00:00.000Z","type":"date"},{"key":"出行方式","value":"高铁","type":"string"},{"key":"车次/车厢/座位","value":"","type":"string"},{"key":"起始（上车）地","value":"武汉","type":"string"},{"key":"目的（下车）地","value":"柳州","type":"string"},{"key":"地点","value":"","type":"string"},{"key":"事件","value":"","type":"string"},{"key":"开始时间","value":"","type":"date"},{"key":"结束时间","value":"","type":"date"},{"key":"数据源1","value":"http://app-h5.ngzb.com.cn/shareArticle?news_id=31777144&from=groupmessage&isappinstalled=0","type":"url"},{"key":"数据源2","value":"","type":"url"},{"key":"审核状态","value":"已审核","type":"enum"}],[{"key":"是否湖北居民","value":"否","type":"enum"},{"key":"患者编号","value":"0772000004","type":"string"},{"key":"患者名","value":"付某","type":"string"},{"key":"省","value":"湖北省","type":"string"},{"key":"市","value":"随州市","type":"string"},{"key":"区/县","value":"","type":"string"},{"key":"镇/街道","value":"","type":"string"},{"key":"年龄","value":46,"type":"int"},{"key":"性别","value":"男","type":"enum"},{"key":"密切患者","value":"","type":"string"},{"key":"离鄂时间","value":"2020-01-12T16:00:00.000Z","type":"date"},{"key":"离鄂城市","value":"武汉","type":"string"},{"key":"发病日期","value":"2020-01-24T16:00:00.000Z","type":"date"},{"key":"发病地点","value":"柳州市","type":"string"},{"key":"确诊日期","value":"2020-01-25T16:00:00.000Z","type":"date"},{"key":"确诊医院","value":"柳铁中心医院","type":"string"},{"key":"病症","value":"","type":"string"},{"key":"密触人数","value":10,"type":"string"},{"key":"时间","value":"2020-01-12T16:00:00.000Z","type":"date"},{"key":"出行方式","value":"火车","type":"string"},{"key":"车次/车厢/座位","value":"","type":"string"},{"key":"起始（上车）地","value":"武汉","type":"string"},{"key":"目的（下车）地","value":"柳州","type":"string"},{"key":"地点","value":"","type":"string"},{"key":"事件","value":"武汉转乘","type":"string"},{"key":"开始时间","value":"2020-01-11T16:00:00.000Z","type":"date"},{"key":"结束时间","value":"2020-01-12T16:00:00.000Z","type":"date"},{"key":"数据源1","value":"http://app-h5.ngzb.com.cn/shareArticle?news_id=31777144&from=groupmessage&isappinstalled=0","type":"url"},{"key":"数据源2","value":"","type":"url"},{"key":"审核状态","value":"已审核","type":"enum"}],[{"key":"是否湖北居民","value":"","type":"enum{是,否}"},{"key":"患者编号","value":"","type":"string"},{"key":"患者名","value":"","type":"string"},{"key":"省","value":"","type":"string"},{"key":"市","value":"","type":"string"},{"key":"区/县","value":"","type":"string"},{"key":"镇/街道","value":"","type":"string"},{"key":"年龄","value":0,"type":"int"},{"key":"性别","value":"","type":"enum{男,女}"},{"key":"密切患者","value":"","type":"string"},{"key":"离鄂时间","value":"","type":"date"},{"key":"离鄂城市","value":"","type":"string"},{"key":"发病日期","value":"","type":"date"},{"key":"发病地点","value":"","type":"string"},{"key":"确诊日期","value":"","type":"date"},{"key":"确诊医院","value":"","type":"string"},{"key":"病症","value":"","type":"string"},{"key":"密触人数","value":"","type":"string"},{"key":"时间","value":"","type":"date"},{"key":"出行方式","value":"","type":"string"},{"key":"车次/车厢/座位","value":"","type":"string"},{"key":"起始（上车）地","value":"","type":"string"},{"key":"目的（下车）地","value":"","type":"string"},{"key":"地点","value":"","type":"string"},{"key":"事件","value":"随州探亲","type":"string"},{"key":"开始时间","value":"2020-01-08T16:00:00.000Z","type":"date"},{"key":"结束时间","value":"2020-01-11T16:00:00.000Z","type":"date"},{"key":"数据源1","value":"http://app-h5.ngzb.com.cn/shareArticle?news_id=31777144&from=groupmessage&isappinstalled=0","type":"url"},{"key":"数据源2","value":"","type":"url"},{"key":"审核状态","value":"已审核","type":"enum"}],[{"key":"是否湖北居民","value":"是","type":"enum"},{"key":"患者编号","value":"0772000005","type":"string"},{"key":"患者名","value":"杨某","type":"string"},{"key":"省","value":"湖北省","type":"string"},{"key":"市","value":"孝感市","type":"string"},{"key":"区/县","value":"大悟县","type":"string"},{"key":"镇/街道","value":"","type":"string"},{"key":"年龄","value":27,"type":"int"},{"key":"性别","value":"女","type":"enum"},{"key":"密切患者","value":"","type":"string"},{"key":"离鄂时间","value":"2020-01-21T16:00:00.000Z","type":"date"},{"key":"离鄂城市","value":"武汉","type":"string"},{"key":"发病日期","value":"2020-01-21T16:00:00.000Z","type":"date"},{"key":"发病地点","value":"柳州市","type":"string"},{"key":"确诊日期","value":"2020-01-28T16:00:00.000Z","type":"date"},{"key":"确诊医院","value":"柳州市人民医院","type":"string"},{"key":"病症","value":"呼吸道症状","type":"string"},{"key":"密触人数","value":"","type":"string"},{"key":"时间","value":"2020-01-21T16:00:00.000Z","type":"date"},{"key":"出行方式","value":"火车","type":"string"},{"key":"车次/车厢/座位","value":"Z335","type":"string"},{"key":"起始（上车）地","value":"武汉","type":"string"},{"key":"目的（下车）地","value":"柳州","type":"string"},{"key":"地点","value":"","type":"string"},{"key":"事件","value":"","type":"string"},{"key":"开始时间","value":"","type":"date"},{"key":"结束时间","value":"","type":"date"},{"key":"数据源1","value":"http://app-h5.ngzb.com.cn/shareArticle?news_id=31777144&from=groupmessage&isappinstalled=0","type":"url"},{"key":"数据源2","value":"","type":"url"},{"key":"审核状态","value":"已审核","type":"enum"}],[{"key":"是否湖北居民","value":"是","type":"enum"},{"key":"患者编号","value":"0772000006","type":"string"},{"key":"患者名","value":"李某","type":"string"},{"key":"省","value":"湖北省","type":"string"},{"key":"市","value":"孝感市","type":"string"},{"key":"区/县","value":"大悟县","type":"string"},{"key":"镇/街道","value":"","type":"string"},{"key":"年龄","value":41,"type":"int"},{"key":"性别","value":"男","type":"enum"},{"key":"密切患者","value":772000007,"type":"string"},{"key":"离鄂时间","value":"2020-01-21T16:00:00.000Z","type":"date"},{"key":"离鄂城市","value":"武汉","type":"string"},{"key":"发病日期","value":"2020-01-24T16:00:00.000Z","type":"date"},{"key":"发病地点","value":"柳州市","type":"string"},{"key":"确诊日期","value":"2020-01-28T16:00:00.000Z","type":"date"},{"key":"确诊医院","value":"柳州市人民医院","type":"string"},{"key":"病症","value":"呼吸道症状","type":"string"},{"key":"密触人数","value":"","type":"string"},{"key":"时间","value":"2020-01-21T16:00:00.000Z","type":"date"},{"key":"出行方式","value":"火车","type":"string"},{"key":"车次/车厢/座位","value":"Z335","type":"string"},{"key":"起始（上车）地","value":"武汉","type":"string"},{"key":"目的（下车）地","value":"柳州","type":"string"},{"key":"地点","value":"","type":"string"},{"key":"事件","value":"","type":"string"},{"key":"开始时间","value":"","type":"date"},{"key":"结束时间","value":"","type":"date"},{"key":"数据源1","value":"http://app-h5.ngzb.com.cn/shareArticle?news_id=31777144&from=groupmessage&isappinstalled=0","type":"url"},{"key":"数据源2","value":"","type":"url"},{"key":"审核状态","value":"已审核","type":"enum"}],[{"key":"是否湖北居民","value":"是","type":"enum"},{"key":"患者编号","value":"0772000007","type":"string"},{"key":"患者名","value":"李某","type":"string"},{"key":"省","value":"湖北省","type":"string"},{"key":"市","value":"孝感市","type":"string"},{"key":"区/县","value":"大悟县","type":"string"},{"key":"镇/街道","value":"","type":"string"},{"key":"年龄","value":6,"type":"int"},{"key":"性别","value":"男","type":"enum"},{"key":"密切患者","value":772000006,"type":"string"},{"key":"离鄂时间","value":"2020-01-21T16:00:00.000Z","type":"date"},{"key":"离鄂城市","value":"武汉","type":"string"},{"key":"发病日期","value":"2020-01-25T16:00:00.000Z","type":"date"},{"key":"发病地点","value":"柳州市","type":"string"},{"key":"确诊日期","value":"2020-01-28T16:00:00.000Z","type":"date"},{"key":"确诊医院","value":"柳州市人民医院","type":"string"},{"key":"病症","value":"呼吸道症状","type":"string"},{"key":"密触人数","value":"","type":"string"},{"key":"时间","value":"2020-01-21T16:00:00.000Z","type":"date"},{"key":"出行方式","value":"火车","type":"string"},{"key":"车次/车厢/座位","value":"Z335","type":"string"},{"key":"起始（上车）地","value":"武汉","type":"string"},{"key":"目的（下车）地","value":"柳州","type":"string"},{"key":"地点","value":"","type":"string"},{"key":"事件","value":"","type":"string"},{"key":"开始时间","value":"","type":"date"},{"key":"结束时间","value":"","type":"date"},{"key":"数据源1","value":"http://app-h5.ngzb.com.cn/shareArticle?news_id=31777144&from=groupmessage&isappinstalled=0","type":"url"},{"key":"数据源2","value":"","type":"url"},{"key":"审核状态","value":"已审核","type":"enum"}],[{"key":"是否湖北居民","value":"否","type":"enum"},{"key":"患者编号","value":"0772000008","type":"string"},{"key":"患者名","value":"杨某","type":"string"},{"key":"省","value":"湖北省","type":"string"},{"key":"市","value":"孝感市","type":"string"},{"key":"区/县","value":"大悟县","type":"string"},{"key":"镇/街道","value":"","type":"string"},{"key":"年龄","value":65,"type":"int"},{"key":"性别","value":"男","type":"enum"},{"key":"密切患者","value":"","type":"string"},{"key":"离鄂时间","value":"","type":"date"},{"key":"离鄂城市","value":"","type":"string"},{"key":"发病日期","value":"2020-01-27T16:00:00.000Z","type":"date"},{"key":"发病地点","value":"柳州市","type":"string"},{"key":"确诊日期","value":"2020-01-28T16:00:00.000Z","type":"date"},{"key":"确诊医院","value":"柳州市人民医院","type":"string"},{"key":"病症","value":"呼吸道症状","type":"string"},{"key":"密触人数","value":4,"type":"string"},{"key":"时间","value":"","type":"date"},{"key":"出行方式","value":"","type":"string"},{"key":"车次/车厢/座位","value":"","type":"string"},{"key":"起始（上车）地","value":"","type":"string"},{"key":"目的（下车）地","value":"","type":"string"},{"key":"地点","value":"","type":"string"},{"key":"事件","value":"","type":"string"},{"key":"开始时间","value":"","type":"date"},{"key":"结束时间","value":"","type":"date"},{"key":"数据源1","value":"http://app-h5.ngzb.com.cn/shareArticle?news_id=31777144&from=groupmessage&isappinstalled=0","type":"url"},{"key":"数据源2","value":"","type":"url"},{"key":"审核状态","value":"已审核","type":"enum"}],[{"key":"是否湖北居民","value":"否","type":"enum"},{"key":"患者编号","value":"0772000009","type":"string"},{"key":"患者名","value":"许某","type":"string"},{"key":"省","value":"广西省","type":"string"},{"key":"市","value":"柳州市","type":"string"},{"key":"区/县","value":"鹿寨县","type":"string"},{"key":"镇/街道","value":"","type":"string"},{"key":"年龄","value":21,"type":"int"},{"key":"性别","value":"女","type":"enum"},{"key":"密切患者","value":"","type":"string"},{"key":"离鄂时间","value":"2020-01-19T16:00:00.000Z","type":"date"},{"key":"离鄂城市","value":"武汉","type":"string"},{"key":"发病日期","value":"2020-01-25T16:00:00.000Z","type":"date"},{"key":"发病地点","value":"鹿寨县","type":"string"},{"key":"确诊日期","value":"2020-01-29T16:00:00.000Z","type":"date"},{"key":"确诊医院","value":"鹿寨县人民医院","type":"string"},{"key":"病症","value":"发热","type":"string"},{"key":"密触人数","value":5,"type":"string"},{"key":"时间","value":"2020-01-15T16:00:00.000Z","type":"date"},{"key":"出行方式","value":"飞机","type":"string"},{"key":"车次/车厢/座位","value":"","type":"string"},{"key":"起始（上车）地","value":"柳州","type":"string"},{"key":"目的（下车）地","value":"武汉","type":"string"},{"key":"地点","value":"","type":"string"},{"key":"事件","value":"","type":"string"},{"key":"开始时间","value":"","type":"date"},{"key":"结束时间","value":"","type":"date"},{"key":"数据源1","value":"http://app-h5.ngzb.com.cn/shareArticle?news_id=31777144&from=groupmessage&isappinstalled=0","type":"url"},{"key":"数据源2","value":"","type":"url"},{"key":"审核状态","value":"已审核","type":"enum"}],[{"key":"是否湖北居民","value":"","type":"enum{是,否}"},{"key":"患者编号","value":"","type":"string"},{"key":"患者名","value":"","type":"string"},{"key":"省","value":"","type":"string"},{"key":"市","value":"","type":"string"},{"key":"区/县","value":"","type":"string"},{"key":"镇/街道","value":"","type":"string"},{"key":"年龄","value":0,"type":"int"},{"key":"性别","value":"","type":"enum{男,女}"},{"key":"密切患者","value":"","type":"string"},{"key":"离鄂时间","value":"","type":"date"},{"key":"离鄂城市","value":"","type":"string"},{"key":"发病日期","value":"","type":"date"},{"key":"发病地点","value":"","type":"string"},{"key":"确诊日期","value":"","type":"date"},{"key":"确诊医院","value":"","type":"string"},{"key":"病症","value":"","type":"string"},{"key":"密触人数","value":"","type":"string"},{"key":"时间","value":"2020-01-19T16:00:00.000Z","type":"date"},{"key":"出行方式","value":"飞机","type":"string"},{"key":"车次/车厢/座位","value":"MU9690","type":"string"},{"key":"起始（上车）地","value":"武汉","type":"string"},{"key":"目的（下车）地","value":"柳州","type":"string"},{"key":"地点","value":"","type":"string"},{"key":"事件","value":"鹿寨乘公交车探亲","type":"string"},{"key":"开始时间","value":"2020-01-21T16:00:00.000Z","type":"date"},{"key":"结束时间","value":"2020-01-25T16:00:00.000Z","type":"date"},{"key":"数据源1","value":"http://app-h5.ngzb.com.cn/shareArticle?news_id=31777144&from=groupmessage&isappinstalled=0","type":"url"},{"key":"数据源2","value":"","type":"url"},{"key":"审核状态","value":"已审核","type":"enum"}],[{"key":"是否湖北居民","value":"否","type":"enum"},{"key":"患者编号","value":"0772000010","type":"string"},{"key":"患者名","value":"覃某","type":"string"},{"key":"省","value":"广西省","type":"string"},{"key":"市","value":"柳州市","type":"string"},{"key":"区/县","value":"柳北区","type":"string"},{"key":"镇/街道","value":"","type":"string"},{"key":"年龄","value":51,"type":"int"},{"key":"性别","value":"女","type":"enum"},{"key":"密切患者","value":772000005,"type":"string"},{"key":"离鄂时间","value":"","type":"date"},{"key":"离鄂城市","value":"","type":"string"},{"key":"发病日期","value":"2020-01-29T16:00:00.000Z","type":"date"},{"key":"发病地点","value":"柳州市","type":"string"},{"key":"确诊日期","value":"2020-01-30T16:00:00.000Z","type":"date"},{"key":"确诊医院","value":"龙潭医院","type":"string"},{"key":"病症","value":"发热","type":"string"},{"key":"密触人数","value":4,"type":"string"},{"key":"时间","value":"","type":"date"},{"key":"出行方式","value":"","type":"string"},{"key":"车次/车厢/座位","value":"","type":"string"},{"key":"起始（上车）地","value":"","type":"string"},{"key":"目的（下车）地","value":"","type":"string"},{"key":"地点","value":"","type":"string"},{"key":"事件","value":"","type":"string"},{"key":"开始时间","value":"","type":"date"},{"key":"结束时间","value":"","type":"date"},{"key":"数据源1","value":"http://app-h5.ngzb.com.cn/shareArticle?news_id=31777144&from=groupmessage&isappinstalled=0","type":"url"},{"key":"数据源2","value":"","type":"url"},{"key":"审核状态","value":"已审核","type":"enum"}],[{"key":"是否湖北居民","value":"否","type":"enum"},{"key":"患者编号","value":"0772000011","type":"string"},{"key":"患者名","value":"刘某","type":"string"},{"key":"省","value":"广西省","type":"string"},{"key":"市","value":"柳州市","type":"string"},{"key":"区/县","value":"柳北区","type":"string"},{"key":"镇/街道","value":"","type":"string"},{"key":"年龄","value":43,"type":"int"},{"key":"性别","value":"女","type":"enum"},{"key":"密切患者","value":772000012,"type":"string"},{"key":"离鄂时间","value":"","type":"date"},{"key":"离鄂城市","value":"","type":"string"},{"key":"发病日期","value":"2020-01-27T16:00:00.000Z","type":"date"},{"key":"发病地点","value":"柳州市","type":"string"},{"key":"确诊日期","value":"2020-02-01T16:00:00.000Z","type":"date"},{"key":"确诊医院","value":"柳州市人民医院","type":"string"},{"key":"病症","value":"发热咳嗽","type":"string"},{"key":"密触人数","value":"","type":"string"},{"key":"时间","value":"","type":"date"},{"key":"出行方式","value":"","type":"string"},{"key":"车次/车厢/座位","value":"","type":"string"},{"key":"起始（上车）地","value":"","type":"string"},{"key":"目的（下车）地","value":"","type":"string"},{"key":"地点","value":"","type":"string"},{"key":"事件","value":"","type":"string"},{"key":"开始时间","value":"","type":"date"},{"key":"结束时间","value":"","type":"date"},{"key":"数据源1","value":"http://app-h5.ngzb.com.cn/shareArticle?news_id=31777144&from=groupmessage&isappinstalled=0","type":"url"},{"key":"数据源2","value":"","type":"url"},{"key":"审核状态","value":"已审核","type":"enum"}],[{"key":"是否湖北居民","value":"否","type":"enum"},{"key":"患者编号","value":"0772000012","type":"string"},{"key":"患者名","value":"邱某","type":"string"},{"key":"省","value":"广西省","type":"string"},{"key":"市","value":"柳州市","type":"string"},{"key":"区/县","value":"柳北区","type":"string"},{"key":"镇/街道","value":"","type":"string"},{"key":"年龄","value":46,"type":"int"},{"key":"性别","value":"男","type":"enum"},{"key":"密切患者","value":772000011,"type":"string"},{"key":"离鄂时间","value":"","type":"date"},{"key":"离鄂城市","value":"","type":"string"},{"key":"发病日期","value":"2020-01-28T16:00:00.000Z","type":"date"},{"key":"发病地点","value":"柳州市","type":"string"},{"key":"确诊日期","value":"2020-02-01T16:00:00.000Z","type":"date"},{"key":"确诊医院","value":"柳州市人民医院","type":"string"},{"key":"病症","value":"发热咳嗽","type":"string"},{"key":"密触人数","value":"","type":"string"},{"key":"时间","value":"","type":"date"},{"key":"出行方式","value":"","type":"string"},{"key":"车次/车厢/座位","value":"","type":"string"},{"key":"起始（上车）地","value":"","type":"string"},{"key":"目的（下车）地","value":"","type":"string"},{"key":"地点","value":"","type":"string"},{"key":"事件","value":"","type":"string"},{"key":"开始时间","value":"","type":"date"},{"key":"结束时间","value":"","type":"date"},{"key":"数据源1","value":"http://app-h5.ngzb.com.cn/shareArticle?news_id=31777144&from=groupmessage&isappinstalled=0","type":"url"},{"key":"数据源2","value":"","type":"url"},{"key":"审核状态","value":"已审核","type":"enum"}],[{"key":"是否湖北居民","value":"否","type":"enum"},{"key":"患者编号","value":"0772000013","type":"string"},{"key":"患者名","value":"梁某","type":"string"},{"key":"省","value":"广西省","type":"string"},{"key":"市","value":"来宾市","type":"string"},{"key":"区/县","value":"忻城县","type":"string"},{"key":"镇/街道","value":"","type":"string"},{"key":"年龄","value":36,"type":"int"},{"key":"性别","value":"男","type":"enum"},{"key":"密切患者","value":"","type":"string"},{"key":"离鄂时间","value":"","type":"date"},{"key":"离鄂城市","value":"","type":"string"},{"key":"发病日期","value":"2020-01-25T16:00:00.000Z","type":"date"},{"key":"发病地点","value":"柳州市","type":"string"},{"key":"确诊日期","value":"2020-02-02T16:00:00.000Z","type":"date"},{"key":"确诊医院","value":"柳江区人民医院","type":"string"},{"key":"病症","value":"发热咳嗽","type":"string"},{"key":"密触人数","value":"","type":"string"},{"key":"时间","value":"2020-01-17T16:00:00.000Z","type":"date"},{"key":"出行方式","value":"动车","type":"string"},{"key":"车次/车厢/座位","value":"D4566","type":"string"},{"key":"起始（上车）地","value":"肇庆","type":"string"},{"key":"目的（下车）地","value":"桂林西站","type":"string"},{"key":"地点","value":"","type":"string"},{"key":"事件","value":"云浮、肇庆、顺德、佛山旅游","type":"string"},{"key":"开始时间","value":"2020-01-15T16:00:00.000Z","type":"date"},{"key":"结束时间","value":"2020-01-17T16:00:00.000Z","type":"date"},{"key":"数据源1","value":"http://app-h5.ngzb.com.cn/shareArticle?news_id=31777144&from=groupmessage&isappinstalled=0","type":"url"},{"key":"数据源2","value":"","type":"url"},{"key":"审核状态","value":"已审核","type":"enum"}],[{"key":"是否湖北居民","value":"","type":"enum{是,否}"},{"key":"患者编号","value":"","type":"string"},{"key":"患者名","value":"","type":"string"},{"key":"省","value":"","type":"string"},{"key":"市","value":"","type":"string"},{"key":"区/县","value":"","type":"string"},{"key":"镇/街道","value":"","type":"string"},{"key":"年龄","value":0,"type":"int"},{"key":"性别","value":"","type":"enum{男,女}"},{"key":"密切患者","value":"","type":"string"},{"key":"离鄂时间","value":"","type":"date"},{"key":"离鄂城市","value":"","type":"string"},{"key":"发病日期","value":"","type":"date"},{"key":"发病地点","value":"","type":"string"},{"key":"确诊日期","value":"","type":"date"},{"key":"确诊医院","value":"","type":"string"},{"key":"病症","value":"","type":"string"},{"key":"密触人数","value":"","type":"string"},{"key":"时间","value":"2020-01-18T16:00:00.000Z","type":"date"},{"key":"出行方式","value":"动车","type":"string"},{"key":"车次/车厢/座位","value":"D2933","type":"string"},{"key":"起始（上车）地","value":"桂林","type":"string"},{"key":"目的（下车）地","value":"柳州","type":"string"},{"key":"地点","value":"","type":"string"},{"key":"事件","value":"","type":"string"},{"key":"开始时间","value":"","type":"date"},{"key":"结束时间","value":"","type":"date"},{"key":"数据源1","value":"http://app-h5.ngzb.com.cn/shareArticle?news_id=31777144&from=groupmessage&isappinstalled=0","type":"url"},{"key":"数据源2","value":"","type":"url"},{"key":"审核状态","value":"已审核","type":"enum"}],[{"key":"是否湖北居民","value":"是","type":"enum"},{"key":"患者编号","value":"0772000014","type":"string"},{"key":"患者名","value":"杨某","type":"string"},{"key":"省","value":"湖北省","type":"string"},{"key":"市","value":"孝感市","type":"string"},{"key":"区/县","value":"大悟县","type":"string"},{"key":"镇/街道","value":"","type":"string"},{"key":"年龄","value":20,"type":"int"},{"key":"性别","value":"男","type":"enum"},{"key":"密切患者","value":772000005,"type":"string"},{"key":"离鄂时间","value":"2020-01-21T16:00:00.000Z","type":"date"},{"key":"离鄂城市","value":"武汉","type":"string"},{"key":"发病日期","value":"2020-01-30T16:00:00.000Z","type":"date"},{"key":"发病地点","value":"柳州市","type":"string"},{"key":"确诊日期","value":"2020-02-03T16:00:00.000Z","type":"date"},{"key":"确诊医院","value":"柳州市人民医院","type":"string"},{"key":"病症","value":"发热","type":"string"},{"key":"密触人数","value":"","type":"string"},{"key":"时间","value":"2020-01-21T16:00:00.000Z","type":"date"},{"key":"出行方式","value":"火车","type":"string"},{"key":"车次/车厢/座位","value":"Z335","type":"string"},{"key":"起始（上车）地","value":"武汉","type":"string"},{"key":"目的（下车）地","value":"柳州","type":"string"},{"key":"地点","value":"","type":"string"},{"key":"事件","value":"","type":"string"},{"key":"开始时间","value":"","type":"date"},{"key":"结束时间","value":"","type":"date"},{"key":"数据源1","value":"http://app-h5.ngzb.com.cn/shareArticle?news_id=31777144&from=groupmessage&isappinstalled=0","type":"url"},{"key":"数据源2","value":"","type":"url"},{"key":"审核状态","value":"已审核","type":"enum"}],[{"key":"是否湖北居民","value":"是","type":"enum"},{"key":"患者编号","value":"0772000015","type":"string"},{"key":"患者名","value":"李某","type":"string"},{"key":"省","value":"湖北省","type":"string"},{"key":"市","value":"孝感市","type":"string"},{"key":"区/县","value":"大悟县","type":"string"},{"key":"镇/街道","value":"","type":"string"},{"key":"年龄","value":2,"type":"int"},{"key":"性别","value":"男","type":"enum"},{"key":"密切患者","value":772000005,"type":"string"},{"key":"离鄂时间","value":"2020-01-21T16:00:00.000Z","type":"date"},{"key":"离鄂城市","value":"武汉","type":"string"},{"key":"发病日期","value":"2020-01-30T16:00:00.000Z","type":"date"},{"key":"发病地点","value":"柳州市","type":"string"},{"key":"确诊日期","value":"2020-02-03T16:00:00.000Z","type":"date"},{"key":"确诊医院","value":"柳州市人民医院","type":"string"},{"key":"病症","value":"发热流涕","type":"string"},{"key":"密触人数","value":"","type":"string"},{"key":"时间","value":"2020-01-21T16:00:00.000Z","type":"date"},{"key":"出行方式","value":"火车","type":"string"},{"key":"车次/车厢/座位","value":"Z335","type":"string"},{"key":"起始（上车）地","value":"武汉","type":"string"},{"key":"目的（下车）地","value":"柳州","type":"string"},{"key":"地点","value":"","type":"string"},{"key":"事件","value":"","type":"string"},{"key":"开始时间","value":"","type":"date"},{"key":"结束时间","value":"","type":"date"},{"key":"数据源1","value":"http://app-h5.ngzb.com.cn/shareArticle?news_id=31777144&from=groupmessage&isappinstalled=0","type":"url"},{"key":"数据源2","value":"","type":"url"},{"key":"审核状态","value":"已审核","type":"enum"}],[{"key":"是否湖北居民","value":"否","type":"enum"},{"key":"患者编号","value":"0772000016","type":"string"},{"key":"患者名","value":"李某","type":"string"},{"key":"省","value":"广西省","type":"string"},{"key":"市","value":"柳州市","type":"string"},{"key":"区/县","value":"柳东新区","type":"string"},{"key":"镇/街道","value":"","type":"string"},{"key":"年龄","value":45,"type":"int"},{"key":"性别","value":"女","type":"enum"},{"key":"密切患者","value":"","type":"string"},{"key":"离鄂时间","value":"","type":"date"},{"key":"离鄂城市","value":"","type":"string"},{"key":"发病日期","value":"2020-01-31T16:00:00.000Z","type":"date"},{"key":"发病地点","value":"柳州市","type":"string"},{"key":"确诊日期","value":"2020-02-04T16:00:00.000Z","type":"date"},{"key":"确诊医院","value":"柳州市人民医院","type":"string"},{"key":"病症","value":"头昏咳嗽","type":"string"},{"key":"密触人数","value":"","type":"string"},{"key":"时间","value":"2020-01-26T16:00:00.000Z","type":"date"},{"key":"出行方式","value":"飞机","type":"string"},{"key":"车次/车厢/座位","value":"TR114","type":"string"},{"key":"起始（上车）地","value":"新加坡","type":"string"},{"key":"目的（下车）地","value":"南宁","type":"string"},{"key":"地点","value":"","type":"string"},{"key":"事件","value":"乘坐机场大巴","type":"string"},{"key":"开始时间","value":"2020-01-26T16:00:00.000Z","type":"date"},{"key":"结束时间","value":"2020-01-26T16:00:00.000Z","type":"date"},{"key":"数据源1","value":"http://app-h5.ngzb.com.cn/shareArticle?news_id=31777144&from=groupmessage&isappinstalled=0","type":"url"},{"key":"数据源2","value":"","type":"url"},{"key":"审核状态","value":"已审核","type":"enum"}],[{"key":"是否湖北居民","value":"","type":"enum{是,否}"},{"key":"患者编号","value":"","type":"string"},{"key":"患者名","value":"","type":"string"},{"key":"省","value":"","type":"string"},{"key":"市","value":"","type":"string"},{"key":"区/县","value":"","type":"string"},{"key":"镇/街道","value":"","type":"string"},{"key":"年龄","value":0,"type":"int"},{"key":"性别","value":"","type":"enum{男,女}"},{"key":"密切患者","value":"","type":"string"},{"key":"离鄂时间","value":"","type":"date"},{"key":"离鄂城市","value":"","type":"string"},{"key":"发病日期","value":"","type":"date"},{"key":"发病地点","value":"","type":"string"},{"key":"确诊日期","value":"","type":"date"},{"key":"确诊医院","value":"","type":"string"},{"key":"病症","value":"","type":"string"},{"key":"密触人数","value":"","type":"string"},{"key":"时间","value":"2020-01-26T16:00:00.000Z","type":"date"},{"key":"出行方式","value":"动车","type":"string"},{"key":"车次/车厢/座位","value":"D3934","type":"string"},{"key":"起始（上车）地","value":"南宁","type":"string"},{"key":"目的（下车）地","value":"柳州","type":"string"},{"key":"地点","value":"","type":"string"},{"key":"事件","value":"","type":"string"},{"key":"开始时间","value":"","type":"date"},{"key":"结束时间","value":"","type":"date"},{"key":"数据源1","value":"http://app-h5.ngzb.com.cn/shareArticle?news_id=31777144&from=groupmessage&isappinstalled=0","type":"url"},{"key":"数据源2","value":"","type":"url"},{"key":"审核状态","value":"已审核","type":"enum"}],[{"key":"是否湖北居民","value":"否","type":"enum"},{"key":"患者编号","value":"0772000017","type":"string"},{"key":"患者名","value":"李某","type":"string"},{"key":"省","value":"广西省","type":"string"},{"key":"市","value":"柳州市","type":"string"},{"key":"区/县","value":"柳南区","type":"string"},{"key":"镇/街道","value":"","type":"string"},{"key":"年龄","value":20,"type":"int"},{"key":"性别","value":"男","type":"enum"},{"key":"密切患者","value":"","type":"string"},{"key":"离鄂时间","value":"2020-01-19T16:00:00.000Z","type":"date"},{"key":"离鄂城市","value":"武汉","type":"string"},{"key":"发病日期","value":"2020-02-01T16:00:00.000Z","type":"date"},{"key":"发病地点","value":"柳州市","type":"string"},{"key":"确诊日期","value":"2020-02-04T16:00:00.000Z","type":"date"},{"key":"确诊医院","value":"龙潭医院","type":"string"},{"key":"病症","value":"发热","type":"string"},{"key":"密触人数","value":"","type":"string"},{"key":"时间","value":"2020-01-14T16:00:00.000Z","type":"date"},{"key":"出行方式","value":"火车","type":"string"},{"key":"车次/车厢/座位","value":"","type":"string"},{"key":"起始（上车）地","value":"柳州","type":"string"},{"key":"目的（下车）地","value":"武汉","type":"string"},{"key":"地点","value":"","type":"string"},{"key":"事件","value":"","type":"string"},{"key":"开始时间","value":"","type":"date"},{"key":"结束时间","value":"","type":"date"},{"key":"数据源1","value":"http://app-h5.ngzb.com.cn/shareArticle?news_id=31777144&from=groupmessage&isappinstalled=0","type":"url"},{"key":"数据源2","value":"","type":"url"},{"key":"审核状态","value":"已审核","type":"enum"}],[{"key":"是否湖北居民","value":"","type":"enum{是,否}"},{"key":"患者编号","value":"","type":"string"},{"key":"患者名","value":"","type":"string"},{"key":"省","value":"","type":"string"},{"key":"市","value":"","type":"string"},{"key":"区/县","value":"","type":"string"},{"key":"镇/街道","value":"","type":"string"},{"key":"年龄","value":0,"type":"int"},{"key":"性别","value":"","type":"enum{男,女}"},{"key":"密切患者","value":"","type":"string"},{"key":"离鄂时间","value":"","type":"date"},{"key":"离鄂城市","value":"","type":"string"},{"key":"发病日期","value":"","type":"date"},{"key":"发病地点","value":"","type":"string"},{"key":"确诊日期","value":"","type":"date"},{"key":"确诊医院","value":"","type":"string"},{"key":"病症","value":"","type":"string"},{"key":"密触人数","value":"","type":"string"},{"key":"时间","value":"2020-01-19T16:00:00.000Z","type":"date"},{"key":"出行方式","value":"火车","type":"string"},{"key":"车次/车厢/座位","value":"K315","type":"string"},{"key":"起始（上车）地","value":"武汉","type":"string"},{"key":"目的（下车）地","value":"柳州","type":"string"},{"key":"地点","value":"工人医院","type":"string"},{"key":"事件","value":"乘出租车到工人医院","type":"string"},{"key":"开始时间","value":"2020-02-01T16:00:00.000Z","type":"date"},{"key":"结束时间","value":"2020-02-01T16:00:00.000Z","type":"date"},{"key":"数据源1","value":"http://app-h5.ngzb.com.cn/shareArticle?news_id=31777144&from=groupmessage&isappinstalled=0","type":"url"},{"key":"数据源2","value":"","type":"url"},{"key":"审核状态","value":"已审核","type":"enum"}],[{"key":"是否湖北居民","value":"否","type":"enum"},{"key":"患者编号","value":"0772000018","type":"string"},{"key":"患者名","value":"赵某","type":"string"},{"key":"省","value":"广西省","type":"string"},{"key":"市","value":"柳州市","type":"string"},{"key":"区/县","value":"柳南区","type":"string"},{"key":"镇/街道","value":"","type":"string"},{"key":"年龄","value":50,"type":"int"},{"key":"性别","value":"男","type":"enum"},{"key":"密切患者","value":"","type":"string"},{"key":"离鄂时间","value":"","type":"date"},{"key":"离鄂城市","value":"","type":"string"},{"key":"发病日期","value":"2020-01-29T16:00:00.000Z","type":"date"},{"key":"发病地点","value":"柳州市","type":"string"},{"key":"确诊日期","value":"2020-02-04T16:00:00.000Z","type":"date"},{"key":"确诊医院","value":"龙潭医院","type":"string"},{"key":"病症","value":"反复发热","type":"string"},{"key":"密触人数","value":"","type":"string"},{"key":"时间","value":"","type":"date"},{"key":"出行方式","value":"","type":"string"},{"key":"车次/车厢/座位","value":"","type":"string"},{"key":"起始（上车）地","value":"","type":"string"},{"key":"目的（下车）地","value":"","type":"string"},{"key":"地点","value":"","type":"string"},{"key":"事件","value":"桶装水、煤气罐配送工作","type":"string"},{"key":"开始时间","value":"","type":"date"},{"key":"结束时间","value":"","type":"date"},{"key":"数据源1","value":"http://app-h5.ngzb.com.cn/shareArticle?news_id=31777144&from=groupmessage&isappinstalled=0","type":"url"},{"key":"数据源2","value":"","type":"url"},{"key":"审核状态","value":"已审核","type":"enum"}],[{"key":"是否湖北居民","value":"","type":"enum{是,否}"},{"key":"患者编号","value":"","type":"string"},{"key":"患者名","value":"","type":"string"},{"key":"省","value":"","type":"string"},{"key":"市","value":"","type":"string"},{"key":"区/县","value":"","type":"string"},{"key":"镇/街道","value":"","type":"string"},{"key":"年龄","value":0,"type":"int"},{"key":"性别","value":"","type":"enum{男,女}"},{"key":"密切患者","value":"","type":"string"},{"key":"离鄂时间","value":"","type":"date"},{"key":"离鄂城市","value":"","type":"string"},{"key":"发病日期","value":"","type":"date"},{"key":"发病地点","value":"","type":"string"},{"key":"确诊日期","value":"","type":"date"},{"key":"确诊医院","value":"","type":"string"},{"key":"病症","value":"","type":"string"},{"key":"密触人数","value":"","type":"string"},{"key":"时间","value":"","type":"date"},{"key":"出行方式","value":"","type":"string"},{"key":"车次/车厢/座位","value":"","type":"string"},{"key":"起始（上车）地","value":"","type":"string"},{"key":"目的（下车）地","value":"","type":"string"},{"key":"地点","value":"工人医院","type":"string"},{"key":"事件","value":"从鹏飞菜市站坐41路公交到柳州市工人医院","type":"string"},{"key":"开始时间","value":"2020-02-02T16:00:00.000Z","type":"date"},{"key":"结束时间","value":"2020-02-02T16:00:00.000Z","type":"date"},{"key":"数据源1","value":"http://app-h5.ngzb.com.cn/shareArticle?news_id=31777144&from=groupmessage&isappinstalled=0","type":"url"},{"key":"数据源2","value":"","type":"url"},{"key":"审核状态","value":"已审核","type":"enum"}],[{"key":"是否湖北居民","value":"否","type":"enum"},{"key":"患者编号","value":"0772000019","type":"string"},{"key":"患者名","value":"姜某","type":"string"},{"key":"省","value":"广西省","type":"string"},{"key":"市","value":"柳州市","type":"string"},{"key":"区/县","value":"柳北区","type":"string"},{"key":"镇/街道","value":"","type":"string"},{"key":"年龄","value":59,"type":"int"},{"key":"性别","value":"女","type":"enum"},{"key":"密切患者","value":"0772000015/0772000020","type":"string"},{"key":"离鄂时间","value":"","type":"date"},{"key":"离鄂城市","value":"","type":"string"},{"key":"发病日期","value":"2020-02-07T16:00:00.000Z","type":"date"},{"key":"发病地点","value":"柳州市","type":"string"},{"key":"确诊日期","value":"2020-02-08T16:00:00.000Z","type":"date"},{"key":"确诊医院","value":"柳州市人民医院","type":"string"},{"key":"病症","value":"咳嗽","type":"string"},{"key":"密触人数","value":"","type":"string"},{"key":"时间","value":"2020-01-26T16:00:00.000Z","type":"date"},{"key":"出行方式","value":"飞机","type":"string"},{"key":"车次/车厢/座位","value":"TR114","type":"string"},{"key":"起始（上车）地","value":"新加坡","type":"string"},{"key":"目的（下车）地","value":"南宁","type":"string"},{"key":"地点","value":"","type":"string"},{"key":"事件","value":"","type":"string"},{"key":"开始时间","value":"","type":"date"},{"key":"结束时间","value":"","type":"date"},{"key":"数据源1","value":"http://app-h5.ngzb.com.cn/shareArticle?news_id=31777144&from=groupmessage&isappinstalled=0","type":"url"},{"key":"数据源2","value":"","type":"url"},{"key":"审核状态","value":"已审核","type":"enum"}],[{"key":"是否湖北居民","value":"","type":"enum{是,否}"},{"key":"患者编号","value":"","type":"string"},{"key":"患者名","value":"","type":"string"},{"key":"省","value":"","type":"string"},{"key":"市","value":"","type":"string"},{"key":"区/县","value":"","type":"string"},{"key":"镇/街道","value":"","type":"string"},{"key":"年龄","value":0,"type":"int"},{"key":"性别","value":"","type":"enum{男,女}"},{"key":"密切患者","value":"","type":"string"},{"key":"离鄂时间","value":"","type":"date"},{"key":"离鄂城市","value":"","type":"string"},{"key":"发病日期","value":"","type":"date"},{"key":"发病地点","value":"","type":"string"},{"key":"确诊日期","value":"","type":"date"},{"key":"确诊医院","value":"","type":"string"},{"key":"病症","value":"","type":"string"},{"key":"密触人数","value":"","type":"string"},{"key":"时间","value":"2020-01-26T16:00:00.000Z","type":"date"},{"key":"出行方式","value":"动车","type":"string"},{"key":"车次/车厢/座位","value":"D3934","type":"string"},{"key":"起始（上车）地","value":"南宁","type":"string"},{"key":"目的（下车）地","value":"柳州","type":"string"},{"key":"地点","value":"","type":"string"},{"key":"事件","value":"","type":"string"},{"key":"开始时间","value":"","type":"date"},{"key":"结束时间","value":"","type":"date"},{"key":"数据源1","value":"http://app-h5.ngzb.com.cn/shareArticle?news_id=31777144&from=groupmessage&isappinstalled=0","type":"url"},{"key":"数据源2","value":"","type":"url"},{"key":"审核状态","value":"已审核","type":"enum"}],[{"key":"是否湖北居民","value":"","type":"enum{是,否}"},{"key":"患者编号","value":"","type":"string"},{"key":"患者名","value":"","type":"string"},{"key":"省","value":"","type":"string"},{"key":"市","value":"","type":"string"},{"key":"区/县","value":"","type":"string"},{"key":"镇/街道","value":"","type":"string"},{"key":"年龄","value":0,"type":"int"},{"key":"性别","value":"","type":"enum{男,女}"},{"key":"密切患者","value":"","type":"string"},{"key":"离鄂时间","value":"","type":"date"},{"key":"离鄂城市","value":"","type":"string"},{"key":"发病日期","value":"","type":"date"},{"key":"发病地点","value":"","type":"string"},{"key":"确诊日期","value":"","type":"date"},{"key":"确诊医院","value":"","type":"string"},{"key":"病症","value":"","type":"string"},{"key":"密触人数","value":"","type":"string"},{"key":"时间","value":"2020-01-27T10:00:00.000Z","type":"date"},{"key":"出行方式","value":"公交","type":"string"},{"key":"车次/车厢/座位","value":"2路","type":"string"},{"key":"起始（上车）地","value":"柳州火车站","type":"string"},{"key":"目的（下车）地","value":"北站路","type":"string"},{"key":"地点","value":"","type":"string"},{"key":"事件","value":"","type":"string"},{"key":"开始时间","value":"","type":"date"},{"key":"结束时间","value":"","type":"date"},{"key":"数据源1","value":"http://app-h5.ngzb.com.cn/shareArticle?news_id=31777144&from=groupmessage&isappinstalled=0","type":"url"},{"key":"数据源2","value":"","type":"url"},{"key":"审核状态","value":"已审核","type":"enum"}],[{"key":"是否湖北居民","value":"否","type":"enum"},{"key":"患者编号","value":"0772000020","type":"string"},{"key":"患者名","value":"刘某","type":"string"},{"key":"省","value":"广西省","type":"string"},{"key":"市","value":"柳州市","type":"string"},{"key":"区/县","value":"柳北区","type":"string"},{"key":"镇/街道","value":"","type":"string"},{"key":"年龄","value":36,"type":"int"},{"key":"性别","value":"男","type":"enum"},{"key":"密切患者","value":"0772000015/0772000019","type":"string"},{"key":"离鄂时间","value":"","type":"date"},{"key":"离鄂城市","value":"","type":"string"},{"key":"发病日期","value":"2020-02-07T16:00:00.000Z","type":"date"},{"key":"发病地点","value":"柳州市","type":"string"},{"key":"确诊日期","value":"2020-02-08T16:00:00.000Z","type":"date"},{"key":"确诊医院","value":"柳州市人民医院","type":"string"},{"key":"病症","value":"咳嗽","type":"string"},{"key":"密触人数","value":"","type":"string"},{"key":"时间","value":"2020-01-26T16:00:00.000Z","type":"date"},{"key":"出行方式","value":"飞机","type":"string"},{"key":"车次/车厢/座位","value":"TR114","type":"string"},{"key":"起始（上车）地","value":"新加坡","type":"string"},{"key":"目的（下车）地","value":"南宁","type":"string"},{"key":"地点","value":"","type":"string"},{"key":"事件","value":"","type":"string"},{"key":"开始时间","value":"","type":"date"},{"key":"结束时间","value":"","type":"date"},{"key":"数据源1","value":"http://app-h5.ngzb.com.cn/shareArticle?news_id=31777144&from=groupmessage&isappinstalled=0","type":"url"},{"key":"数据源2","value":"","type":"url"},{"key":"审核状态","value":"已审核","type":"enum"}],[{"key":"是否湖北居民","value":"","type":"enum{是,否}"},{"key":"患者编号","value":"","type":"string"},{"key":"患者名","value":"","type":"string"},{"key":"省","value":"","type":"string"},{"key":"市","value":"","type":"string"},{"key":"区/县","value":"","type":"string"},{"key":"镇/街道","value":"","type":"string"},{"key":"年龄","value":0,"type":"int"},{"key":"性别","value":"","type":"enum{男,女}"},{"key":"密切患者","value":"","type":"string"},{"key":"离鄂时间","value":"","type":"date"},{"key":"离鄂城市","value":"","type":"string"},{"key":"发病日期","value":"","type":"date"},{"key":"发病地点","value":"","type":"string"},{"key":"确诊日期","value":"","type":"date"},{"key":"确诊医院","value":"","type":"string"},{"key":"病症","value":"","type":"string"},{"key":"密触人数","value":"","type":"string"},{"key":"时间","value":"2020-01-26T16:00:00.000Z","type":"date"},{"key":"出行方式","value":"动车","type":"string"},{"key":"车次/车厢/座位","value":"D3934","type":"string"},{"key":"起始（上车）地","value":"南宁","type":"string"},{"key":"目的（下车）地","value":"柳州","type":"string"},{"key":"地点","value":"","type":"string"},{"key":"事件","value":"","type":"string"},{"key":"开始时间","value":"","type":"date"},{"key":"结束时间","value":"","type":"date"},{"key":"数据源1","value":"http://app-h5.ngzb.com.cn/shareArticle?news_id=31777144&from=groupmessage&isappinstalled=0","type":"url"},{"key":"数据源2","value":"","type":"url"},{"key":"审核状态","value":"已审核","type":"enum"}],[{"key":"是否湖北居民","value":"","type":"enum{是,否}"},{"key":"患者编号","value":"","type":"string"},{"key":"患者名","value":"","type":"string"},{"key":"省","value":"","type":"string"},{"key":"市","value":"","type":"string"},{"key":"区/县","value":"","type":"string"},{"key":"镇/街道","value":"","type":"string"},{"key":"年龄","value":0,"type":"int"},{"key":"性别","value":"","type":"enum{男,女}"},{"key":"密切患者","value":"","type":"string"},{"key":"离鄂时间","value":"","type":"date"},{"key":"离鄂城市","value":"","type":"string"},{"key":"发病日期","value":"","type":"date"},{"key":"发病地点","value":"","type":"string"},{"key":"确诊日期","value":"","type":"date"},{"key":"确诊医院","value":"","type":"string"},{"key":"病症","value":"","type":"string"},{"key":"密触人数","value":"","type":"string"},{"key":"时间","value":"2020-01-27T10:00:00.000Z","type":"date"},{"key":"出行方式","value":"公交","type":"string"},{"key":"车次/车厢/座位","value":"2路","type":"string"},{"key":"起始（上车）地","value":"柳州火车站","type":"string"},{"key":"目的（下车）地","value":"北站路","type":"string"},{"key":"地点","value":"","type":"string"},{"key":"事件","value":"","type":"string"},{"key":"开始时间","value":"","type":"date"},{"key":"结束时间","value":"","type":"date"},{"key":"数据源1","value":"http://app-h5.ngzb.com.cn/shareArticle?news_id=31777144&from=groupmessage&isappinstalled=0","type":"url"},{"key":"数据源2","value":"","type":"url"},{"key":"审核状态","value":"已审核","type":"enum"}],[{"key":"是否湖北居民","value":"","type":"enum{是,否}"},{"key":"患者编号","value":"","type":"string"},{"key":"患者名","value":"","type":"string"},{"key":"省","value":"","type":"string"},{"key":"市","value":"","type":"string"},{"key":"区/县","value":"","type":"string"},{"key":"镇/街道","value":"","type":"string"},{"key":"年龄","value":0,"type":"int"},{"key":"性别","value":"","type":"enum{男,女}"},{"key":"密切患者","value":"","type":"string"},{"key":"离鄂时间","value":"","type":"date"},{"key":"离鄂城市","value":"","type":"string"},{"key":"发病日期","value":"","type":"date"},{"key":"发病地点","value":"","type":"string"},{"key":"确诊日期","value":"","type":"date"},{"key":"确诊医院","value":"","type":"string"},{"key":"病症","value":"","type":"string"},{"key":"密触人数","value":"","type":"string"},{"key":"时间","value":"","type":"date"},{"key":"出行方式","value":"","type":"string"},{"key":"车次/车厢/座位","value":"","type":"string"},{"key":"起始（上车）地","value":"","type":"string"},{"key":"目的（下车）地","value":"","type":"string"},{"key":"地点","value":"","type":"string"},{"key":"事件","value":"","type":"string"},{"key":"开始时间","value":"","type":"date"},{"key":"结束时间","value":"","type":"date"},{"key":"数据源1","value":"","type":"url"},{"key":"数据源2","value":"","type":"url"},{"key":"审核状态","value":"已审核","type":"enum"}],[{"key":"是否湖北居民","value":"是","type":"enum"},{"key":"患者编号","value":"0772000021","type":"string"},{"key":"患者名","value":"王某","type":"string"},{"key":"省","value":"湖北省","type":"string"},{"key":"市","value":"武汉市","type":"string"},{"key":"区/县","value":"武昌区","type":"string"},{"key":"镇/街道","value":"","type":"string"},{"key":"年龄","value":0,"type":"int"},{"key":"性别","value":"女","type":"enum"},{"key":"密切患者","value":"","type":"string"},{"key":"离鄂时间","value":"","type":"date"},{"key":"离鄂城市","value":"","type":"string"},{"key":"发病日期","value":"2020-02-02T16:00:00.000Z","type":"date"},{"key":"发病地点","value":"象州县","type":"string"},{"key":"确诊日期","value":"2020-02-04T16:00:00.000Z","type":"date"},{"key":"确诊医院","value":"来宾市人民医院","type":"string"},{"key":"病症","value":"发热","type":"string"},{"key":"密触人数","value":"","type":"string"},{"key":"时间","value":"","type":"date"},{"key":"出行方式","value":"","type":"string"},{"key":"车次/车厢/座位","value":"","type":"string"},{"key":"起始（上车）地","value":"","type":"string"},{"key":"目的（下车）地","value":"","type":"string"},{"key":"地点","value":"","type":"string"},{"key":"事件","value":"","type":"string"},{"key":"开始时间","value":"","type":"date"},{"key":"结束时间","value":"","type":"date"},{"key":"数据源1","value":"","type":"url"},{"key":"数据源2","value":"","type":"url"},{"key":"审核状态","value":"已审核","type":"enum"}],[{"key":"是否湖北居民","value":"否","type":"enum"},{"key":"患者编号","value":"0772000022","type":"string"},{"key":"患者名","value":"张某","type":"string"},{"key":"省","value":"广西省","type":"string"},{"key":"市","value":"来宾市","type":"string"},{"key":"区/县","value":"兴宾区","type":"string"},{"key":"镇/街道","value":"","type":"string"},{"key":"年龄","value":45,"type":"int"},{"key":"性别","value":"女","type":"enum"},{"key":"密切患者","value":772000023,"type":"string"},{"key":"离鄂时间","value":"","type":"date"},{"key":"离鄂城市","value":"","type":"string"},{"key":"发病日期","value":"2020-02-01T16:00:00.000Z","type":"date"},{"key":"发病地点","value":"来宾市","type":"string"},{"key":"确诊日期","value":"2020-02-05T16:00:00.000Z","type":"date"},{"key":"确诊医院","value":"兴宾区人民医院","type":"string"},{"key":"病症","value":"发热咳嗽","type":"string"},{"key":"密触人数","value":"","type":"string"},{"key":"时间","value":"","type":"date"},{"key":"出行方式","value":"","type":"string"},{"key":"车次/车厢/座位","value":"","type":"string"},{"key":"起始（上车）地","value":"","type":"string"},{"key":"目的（下车）地","value":"","type":"string"},{"key":"地点","value":"","type":"string"},{"key":"事件","value":"与从武汉回来的丈夫密切接触","type":"string"},{"key":"开始时间","value":"","type":"date"},{"key":"结束时间","value":"","type":"date"},{"key":"数据源1","value":"http://app-h5.ngzb.com.cn/shareArticle?news_id=31777144&from=groupmessage&isappinstalled=0","type":"url"},{"key":"数据源2","value":"","type":"url"},{"key":"审核状态","value":"已审核","type":"enum"}],[{"key":"是否湖北居民","value":"否","type":"enum"},{"key":"患者编号","value":"0772000023","type":"string"},{"key":"患者名","value":"韦某","type":"string"},{"key":"省","value":"广西省","type":"string"},{"key":"市","value":"来宾市","type":"string"},{"key":"区/县","value":"兴宾区","type":"string"},{"key":"镇/街道","value":"","type":"string"},{"key":"年龄","value":43,"type":"int"},{"key":"性别","value":"男","type":"enum"},{"key":"密切患者","value":772000022,"type":"string"},{"key":"离鄂时间","value":"","type":"date"},{"key":"离鄂城市","value":"","type":"string"},{"key":"发病日期","value":"2020-02-05T16:00:00.000Z","type":"date"},{"key":"发病地点","value":"来宾市","type":"string"},{"key":"确诊日期","value":"2020-02-06T16:00:00.000Z","type":"date"},{"key":"确诊医院","value":"兴宾区人民医院","type":"string"},{"key":"病症","value":"","type":"string"},{"key":"密触人数","value":"","type":"string"},{"key":"时间","value":"","type":"date"},{"key":"出行方式","value":"","type":"string"},{"key":"车次/车厢/座位","value":"","type":"string"},{"key":"起始（上车）地","value":"武汉","type":"string"},{"key":"目的（下车）地","value":"","type":"string"},{"key":"地点","value":"","type":"string"},{"key":"事件","value":"","type":"string"},{"key":"开始时间","value":"","type":"date"},{"key":"结束时间","value":"","type":"date"},{"key":"数据源1","value":"http://app-h5.ngzb.com.cn/shareArticle?news_id=31777144&from=groupmessage&isappinstalled=0","type":"url"},{"key":"数据源2","value":"","type":"url"},{"key":"审核状态","value":"已审核","type":"enum"}],[{"key":"是否湖北居民","value":"否","type":"enum"},{"key":"患者编号","value":"0772000024","type":"string"},{"key":"患者名","value":"张某","type":"string"},{"key":"省","value":"广西省","type":"string"},{"key":"市","value":"来宾市","type":"string"},{"key":"区/县","value":"兴宾区","type":"string"},{"key":"镇/街道","value":"","type":"string"},{"key":"年龄","value":48,"type":"int"},{"key":"性别","value":"女","type":"enum"},{"key":"密切患者","value":"0772000022/0772000025/0772000026/0772000027","type":"string"},{"key":"离鄂时间","value":"","type":"date"},{"key":"离鄂城市","value":"","type":"string"},{"key":"发病日期","value":"2020-02-06T16:00:00.000Z","type":"date"},{"key":"发病地点","value":"来宾市","type":"string"},{"key":"确诊日期","value":"2020-02-07T16:00:00.000Z","type":"date"},{"key":"确诊医院","value":"来宾市人民医院","type":"string"},{"key":"病症","value":"","type":"string"},{"key":"密触人数","value":"","type":"string"},{"key":"时间","value":"","type":"date"},{"key":"出行方式","value":"","type":"string"},{"key":"车次/车厢/座位","value":"","type":"string"},{"key":"起始（上车）地","value":"","type":"string"},{"key":"目的（下车）地","value":"","type":"string"},{"key":"地点","value":"","type":"string"},{"key":"事件","value":"","type":"string"},{"key":"开始时间","value":"","type":"date"},{"key":"结束时间","value":"","type":"date"},{"key":"数据源1","value":"http://app-h5.ngzb.com.cn/shareArticle?news_id=31777144&from=groupmessage&isappinstalled=0","type":"url"},{"key":"数据源2","value":"","type":"url"},{"key":"审核状态","value":"已审核","type":"enum"}],[{"key":"是否湖北居民","value":"否","type":"enum"},{"key":"患者编号","value":"0772000025","type":"string"},{"key":"患者名","value":"韦某","type":"string"},{"key":"省","value":"广西省","type":"string"},{"key":"市","value":"来宾市","type":"string"},{"key":"区/县","value":"兴宾区","type":"string"},{"key":"镇/街道","value":"","type":"string"},{"key":"年龄","value":48,"type":"int"},{"key":"性别","value":"男","type":"enum"},{"key":"密切患者","value":"0772000022/0772000024/0772000026/0772000027","type":"string"},{"key":"离鄂时间","value":"","type":"date"},{"key":"离鄂城市","value":"","type":"string"},{"key":"发病日期","value":"2020-02-06T16:00:00.000Z","type":"date"},{"key":"发病地点","value":"来宾市","type":"string"},{"key":"确诊日期","value":"2020-02-07T16:00:00.000Z","type":"date"},{"key":"确诊医院","value":"来宾市人民医院","type":"string"},{"key":"病症","value":"","type":"string"},{"key":"密触人数","value":"","type":"string"},{"key":"时间","value":"","type":"date"},{"key":"出行方式","value":"","type":"string"},{"key":"车次/车厢/座位","value":"","type":"string"},{"key":"起始（上车）地","value":"","type":"string"},{"key":"目的（下车）地","value":"","type":"string"},{"key":"地点","value":"","type":"string"},{"key":"事件","value":"","type":"string"},{"key":"开始时间","value":"","type":"date"},{"key":"结束时间","value":"","type":"date"},{"key":"数据源1","value":"http://app-h5.ngzb.com.cn/shareArticle?news_id=31777144&from=groupmessage&isappinstalled=0","type":"url"},{"key":"数据源2","value":"","type":"url"},{"key":"审核状态","value":"已审核","type":"enum"}],[{"key":"是否湖北居民","value":"否","type":"enum"},{"key":"患者编号","value":"0772000026","type":"string"},{"key":"患者名","value":"韦某","type":"string"},{"key":"省","value":"广西省","type":"string"},{"key":"市","value":"来宾市","type":"string"},{"key":"区/县","value":"兴宾区","type":"string"},{"key":"镇/街道","value":"","type":"string"},{"key":"年龄","value":28,"type":"int"},{"key":"性别","value":"男","type":"enum"},{"key":"密切患者","value":"0772000022/0772000024/0772000025/0772000027","type":"string"},{"key":"离鄂时间","value":"","type":"date"},{"key":"离鄂城市","value":"","type":"string"},{"key":"发病日期","value":"2020-02-06T16:00:00.000Z","type":"date"},{"key":"发病地点","value":"来宾市","type":"string"},{"key":"确诊日期","value":"2020-02-07T16:00:00.000Z","type":"date"},{"key":"确诊医院","value":"来宾市人民医院","type":"string"},{"key":"病症","value":"","type":"string"},{"key":"密触人数","value":"","type":"string"},{"key":"时间","value":"","type":"date"},{"key":"出行方式","value":"","type":"string"},{"key":"车次/车厢/座位","value":"","type":"string"},{"key":"起始（上车）地","value":"","type":"string"},{"key":"目的（下车）地","value":"","type":"string"},{"key":"地点","value":"","type":"string"},{"key":"事件","value":"","type":"string"},{"key":"开始时间","value":"","type":"date"},{"key":"结束时间","value":"","type":"date"},{"key":"数据源1","value":"http://app-h5.ngzb.com.cn/shareArticle?news_id=31777144&from=groupmessage&isappinstalled=0","type":"url"},{"key":"数据源2","value":"","type":"url"},{"key":"审核状态","value":"已审核","type":"enum"}],[{"key":"是否湖北居民","value":"否","type":"enum"},{"key":"患者编号","value":"0772000027","type":"string"},{"key":"患者名","value":"韦某","type":"string"},{"key":"省","value":"广西省","type":"string"},{"key":"市","value":"来宾市","type":"string"},{"key":"区/县","value":"兴宾区","type":"string"},{"key":"镇/街道","value":"","type":"string"},{"key":"年龄","value":1,"type":"int"},{"key":"性别","value":"男","type":"enum"},{"key":"密切患者","value":"0772000022/0772000024/0772000025/0772000026","type":"string"},{"key":"离鄂时间","value":"","type":"date"},{"key":"离鄂城市","value":"","type":"string"},{"key":"发病日期","value":"2020-02-06T16:00:00.000Z","type":"date"},{"key":"发病地点","value":"来宾市","type":"string"},{"key":"确诊日期","value":"2020-02-07T16:00:00.000Z","type":"date"},{"key":"确诊医院","value":"来宾市人民医院","type":"string"},{"key":"病症","value":"","type":"string"},{"key":"密触人数","value":"","type":"string"},{"key":"时间","value":"","type":"date"},{"key":"出行方式","value":"","type":"string"},{"key":"车次/车厢/座位","value":"","type":"string"},{"key":"起始（上车）地","value":"","type":"string"},{"key":"目的（下车）地","value":"","type":"string"},{"key":"地点","value":"","type":"string"},{"key":"事件","value":"","type":"string"},{"key":"开始时间","value":"","type":"date"},{"key":"结束时间","value":"","type":"date"},{"key":"数据源1","value":"http://app-h5.ngzb.com.cn/shareArticle?news_id=31777144&from=groupmessage&isappinstalled=0","type":"url"},{"key":"数据源2","value":"","type":"url"},{"key":"审核状态","value":"已审核","type":"enum"}],[{"key":"是否湖北居民","value":"否","type":"enum"},{"key":"患者编号","value":"0772000028","type":"string"},{"key":"患者名","value":"张某","type":"string"},{"key":"省","value":"广西省","type":"string"},{"key":"市","value":"来宾市","type":"string"},{"key":"区/县","value":"兴宾区","type":"string"},{"key":"镇/街道","value":"","type":"string"},{"key":"年龄","value":51,"type":"int"},{"key":"性别","value":"女","type":"enum"},{"key":"密切患者","value":772000022,"type":"string"},{"key":"离鄂时间","value":"","type":"date"},{"key":"离鄂城市","value":"","type":"string"},{"key":"发病日期","value":"2020-02-06T16:00:00.000Z","type":"date"},{"key":"发病地点","value":"来宾市","type":"string"},{"key":"确诊日期","value":"2020-02-08T16:00:00.000Z","type":"date"},{"key":"确诊医院","value":"来宾市人民医院","type":"string"},{"key":"病症","value":"","type":"string"},{"key":"密触人数","value":"","type":"string"},{"key":"时间","value":"","type":"date"},{"key":"出行方式","value":"","type":"string"},{"key":"车次/车厢/座位","value":"","type":"string"},{"key":"起始（上车）地","value":"","type":"string"},{"key":"目的（下车）地","value":"","type":"string"},{"key":"地点","value":"","type":"string"},{"key":"事件","value":"","type":"string"},{"key":"开始时间","value":"","type":"date"},{"key":"结束时间","value":"","type":"date"},{"key":"数据源1","value":"http://app-h5.ngzb.com.cn/shareArticle?news_id=31777144&from=groupmessage&isappinstalled=0","type":"url"},{"key":"数据源2","value":"","type":"url"},{"key":"审核状态","value":"已审核","type":"enum"}],[{"key":"是否湖北居民","value":"否","type":"enum"},{"key":"患者编号","value":"0772000029","type":"string"},{"key":"患者名","value":"程某","type":"string"},{"key":"省","value":"广西省","type":"string"},{"key":"市","value":"来宾市","type":"string"},{"key":"区/县","value":"兴宾区","type":"string"},{"key":"镇/街道","value":"","type":"string"},{"key":"年龄","value":33,"type":"int"},{"key":"性别","value":"男","type":"enum"},{"key":"密切患者","value":772000022,"type":"string"},{"key":"离鄂时间","value":"","type":"date"},{"key":"离鄂城市","value":"","type":"string"},{"key":"发病日期","value":"2020-02-06T16:00:00.000Z","type":"date"},{"key":"发病地点","value":"来宾市","type":"string"},{"key":"确诊日期","value":"2020-02-08T16:00:00.000Z","type":"date"},{"key":"确诊医院","value":"来宾市人民医院","type":"string"},{"key":"病症","value":"","type":"string"},{"key":"密触人数","value":"","type":"string"},{"key":"时间","value":"","type":"date"},{"key":"出行方式","value":"","type":"string"},{"key":"车次/车厢/座位","value":"","type":"string"},{"key":"起始（上车）地","value":"","type":"string"},{"key":"目的（下车）地","value":"","type":"string"},{"key":"地点","value":"","type":"string"},{"key":"事件","value":"","type":"string"},{"key":"开始时间","value":"","type":"date"},{"key":"结束时间","value":"","type":"date"},{"key":"数据源1","value":"http://app-h5.ngzb.com.cn/shareArticle?news_id=31777144&from=groupmessage&isappinstalled=0","type":"url"},{"key":"数据源2","value":"","type":"url"},{"key":"审核状态","value":"已审核","type":"enum"}],[{"key":"是否湖北居民","value":"否","type":"enum"},{"key":"患者编号","value":"0772000030","type":"string"},{"key":"患者名","value":"韦某","type":"string"},{"key":"省","value":"广西省","type":"string"},{"key":"市","value":"来宾市","type":"string"},{"key":"区/县","value":"兴宾区","type":"string"},{"key":"镇/街道","value":"","type":"string"},{"key":"年龄","value":28,"type":"int"},{"key":"性别","value":"女","type":"enum"},{"key":"密切患者","value":772000022,"type":"string"},{"key":"离鄂时间","value":"","type":"date"},{"key":"离鄂城市","value":"","type":"string"},{"key":"发病日期","value":"2020-02-06T16:00:00.000Z","type":"date"},{"key":"发病地点","value":"来宾市","type":"string"},{"key":"确诊日期","value":"2020-02-08T16:00:00.000Z","type":"date"},{"key":"确诊医院","value":"来宾市人民医院","type":"string"},{"key":"病症","value":"","type":"string"},{"key":"密触人数","value":"","type":"string"},{"key":"时间","value":"","type":"date"},{"key":"出行方式","value":"","type":"string"},{"key":"车次/车厢/座位","value":"","type":"string"},{"key":"起始（上车）地","value":"","type":"string"},{"key":"目的（下车）地","value":"","type":"string"},{"key":"地点","value":"","type":"string"},{"key":"事件","value":"","type":"string"},{"key":"开始时间","value":"","type":"date"},{"key":"结束时间","value":"","type":"date"},{"key":"数据源1","value":"http://app-h5.ngzb.com.cn/shareArticle?news_id=31777144&from=groupmessage&isappinstalled=0","type":"url"},{"key":"数据源2","value":"","type":"url"},{"key":"审核状态","value":"已审核","type":"enum"}],[{"key":"是否湖北居民","value":"否","type":"enum"},{"key":"患者编号","value":"0772000031","type":"string"},{"key":"患者名","value":"程某","type":"string"},{"key":"省","value":"广西省","type":"string"},{"key":"市","value":"来宾市","type":"string"},{"key":"区/县","value":"兴宾区","type":"string"},{"key":"镇/街道","value":"","type":"string"},{"key":"年龄","value":1,"type":"int"},{"key":"性别","value":"女","type":"enum"},{"key":"密切患者","value":772000022,"type":"string"},{"key":"离鄂时间","value":"","type":"date"},{"key":"离鄂城市","value":"","type":"string"},{"key":"发病日期","value":"2020-02-06T16:00:00.000Z","type":"date"},{"key":"发病地点","value":"来宾市","type":"string"},{"key":"确诊日期","value":"2020-02-08T16:00:00.000Z","type":"date"},{"key":"确诊医院","value":"来宾市人民医院","type":"string"},{"key":"病症","value":"","type":"string"},{"key":"密触人数","value":"","type":"string"},{"key":"时间","value":"","type":"date"},{"key":"出行方式","value":"","type":"string"},{"key":"车次/车厢/座位","value":"","type":"string"},{"key":"起始（上车）地","value":"","type":"string"},{"key":"目的（下车）地","value":"","type":"string"},{"key":"地点","value":"","type":"string"},{"key":"事件","value":"","type":"string"},{"key":"开始时间","value":"","type":"date"},{"key":"结束时间","value":"","type":"date"},{"key":"数据源1","value":"http://app-h5.ngzb.com.cn/shareArticle?news_id=31777144&from=groupmessage&isappinstalled=0","type":"url"},{"key":"数据源2","value":"","type":"url"},{"key":"审核状态","value":"已审核","type":"enum"}]]