[{"酒店名称":"柏曼酒店黄石大冶琪豪花园店","酒店辖区（县区级）":"黄石大冶市","酒店地址":"大冶大道158号","酒店可提供房间数":null,"酒店可接待人数":null,"联系人":"常军","联系方式":18964151911,"备注":null,"信息发布源链接":"https://m.traveldaily.cn/article/135333?scene=1&clicktime=1580130420&enterid=1580130420&from=singlemessage&isappinstalled=0","审核状态":"已审核"},{"酒店名称":"城市便捷黄石大道店","酒店辖区（县区级）":"西塞山区","酒店地址":"黄石大道242号","酒店可提供房间数":null,"酒店可接待人数":null,"联系人":"熊礼桃","联系方式":15102764275,"备注":null,"信息发布源链接":"https://mp.weixin.qq.com/s/VuCa0DdBtw8vqgxb6P1xGA","审核状态":"已审核"},{"酒店名称":"城市便捷黄石华山路店","酒店辖区（县区级）":"黄石港区","酒店地址":"花湖街道华山路20-6号","酒店可提供房间数":null,"酒店可接待人数":null,"联系人":"张帆","联系方式":13995541362,"备注":null,"信息发布源链接":null,"审核状态":"已审核"},{"酒店名称":"城市便捷阳新经贸大厦店","酒店辖区（县区级）":"阳新县","酒店地址":"兴国大道140号","酒店可提供房间数":null,"酒店可接待人数":null,"联系人":"游振超","联系方式":18772320897,"备注":null,"信息发布源链接":null,"审核状态":"已审核"},{"酒店名称":"城市便捷阳新明月湾店","酒店辖区（县区级）":"阳新县","酒店地址":"湖滨大道新天地商业街1号楼","酒店可提供房间数":null,"酒店可接待人数":null,"联系人":"刘莎","联系方式":15771119463,"备注":null,"信息发布源链接":null,"审核状态":"已审核"}]