[[{"key":"酒店名称","value":"柏曼酒店黄石大冶琪豪花园店","type":"string"},{"key":"酒店辖区（县区级）","value":"黄石大冶市","type":"string"},{"key":"酒店地址","value":"大冶大道158号","type":"string"},{"key":"酒店可提供房间数","value":0,"type":"int"},{"key":"酒店可接待人数","value":0,"type":"int"},{"key":"联系人","value":"常军","type":"string"},{"key":"联系方式","value":[{"name":"","tel":"18964151911"}],"type":"contact"},{"key":"发布时间","value":"2020-01-24T16:00:00.000Z","type":"date"},{"key":"信息发布源链接","value":"https://m.traveldaily.cn/article/135333?scene=1&clicktime=1580130420&enterid=1580130420&from=singlemessage&isappinstalled=0","type":"url"},{"key":"备注","value":"","type":"string"},{"key":"审核状态","value":"已审核","type":"enum"}],[{"key":"酒店名称","value":"城市便捷黄石大道店","type":"string"},{"key":"酒店辖区（县区级）","value":"西塞山区","type":"string"},{"key":"酒店地址","value":"黄石大道242号","type":"string"},{"key":"酒店可提供房间数","value":0,"type":"int"},{"key":"酒店可接待人数","value":0,"type":"int"},{"key":"联系人","value":"熊礼桃","type":"string"},{"key":"联系方式","value":[{"name":"","tel":"15102764275"}],"type":"contact"},{"key":"发布时间","value":"2020-01-24T16:00:00.000Z","type":"date"},{"key":"信息发布源链接","value":"https://mp.weixin.qq.com/s/VuCa0DdBtw8vqgxb6P1xGA","type":"url"},{"key":"备注","value":"","type":"string"},{"key":"审核状态","value":"已审核","type":"enum"}],[{"key":"酒店名称","value":"城市便捷黄石华山路店","type":"string"},{"key":"酒店辖区（县区级）","value":"黄石港区","type":"string"},{"key":"酒店地址","value":"花湖街道华山路20-6号","type":"string"},{"key":"酒店可提供房间数","value":0,"type":"int"},{"key":"酒店可接待人数","value":0,"type":"int"},{"key":"联系人","value":"张帆","type":"string"},{"key":"联系方式","value":[{"name":"","tel":"13995541362"}],"type":"contact"},{"key":"发布时间","value":"2020-01-24T16:00:00.000Z","type":"date"},{"key":"信息发布源链接","value":"https://mp.weixin.qq.com/s/VuCa0DdBtw8vqgxb6P1xGA","type":"url"},{"key":"备注","value":"","type":"string"},{"key":"审核状态","value":"已审核","type":"enum"}],[{"key":"酒店名称","value":"城市便捷阳新经贸大厦店","type":"string"},{"key":"酒店辖区（县区级）","value":"阳新县","type":"string"},{"key":"酒店地址","value":"兴国大道140号","type":"string"},{"key":"酒店可提供房间数","value":0,"type":"int"},{"key":"酒店可接待人数","value":0,"type":"int"},{"key":"联系人","value":"游振超","type":"string"},{"key":"联系方式","value":[{"name":"","tel":"18772320897"}],"type":"contact"},{"key":"发布时间","value":"2020-01-24T16:00:00.000Z","type":"date"},{"key":"信息发布源链接","value":"https://mp.weixin.qq.com/s/VuCa0DdBtw8vqgxb6P1xGA","type":"url"},{"key":"备注","value":"","type":"string"},{"key":"审核状态","value":"已审核","type":"enum"}],[{"key":"酒店名称","value":"城市便捷阳新明月湾店","type":"string"},{"key":"酒店辖区（县区级）","value":"阳新县","type":"string"},{"key":"酒店地址","value":"湖滨大道新天地商业街1号楼","type":"string"},{"key":"酒店可提供房间数","value":0,"type":"int"},{"key":"酒店可接待人数","value":0,"type":"int"},{"key":"联系人","value":"刘莎","type":"string"},{"key":"联系方式","value":[{"name":"","tel":"15771119463"}],"type":"contact"},{"key":"发布时间","value":"2020-01-24T16:00:00.000Z","type":"date"},{"key":"信息发布源链接","value":"https://mp.weixin.qq.com/s/VuCa0DdBtw8vqgxb6P1xGA","type":"url"},{"key":"备注","value":"","type":"string"},{"key":"审核状态","value":"已审核","type":"enum"}]]