[[{"key":"区县","value":"十堰市","type":"string"},{"key":"医院名称","value":"十堰国药东风总医院","type":"string"},{"key":"普通医用口罩","value":1,"type":"supply","specification":"YY/T 0969-2013"},{"key":"医用外科口罩","value":1,"type":"supply","specification":"YY 0469-2010"},{"key":"医用防护口罩 | N95口罩","value":1,"type":"supply","specification":"GB 19083-2010, 建议3M 1860/1870/9123,防飞沫血液体液款"},{"key":"防冲击眼罩/护目镜/防护眼镜","value":1,"type":"supply"},{"key":"防护面罩","value":1,"type":"supply"},{"key":"防护帽/医用帽/圆帽","value":1,"type":"supply"},{"key":"隔离衣","value":1,"type":"supply"},{"key":"防护服","value":1,"type":"supply","specification":"GB 19082-2003"},{"key":"手术衣","value":1,"type":"supply"},{"key":"乳胶手套","value":0,"type":"supply","specification":"灭菌，GB 10213-2006"},{"key":"长筒胶鞋/防污染靴","value":0,"type":"supply"},{"key":"防污染鞋套","value":0,"type":"supply"},{"key":"防污染靴套","value":0,"type":"supply"},{"key":"84消毒液","value":0,"type":"supply"},{"key":"过氧乙酸","value":0,"type":"supply"},{"key":"75%酒精","value":0,"type":"supply"},{"key":"手部皮肤消毒液","value":0,"type":"supply"},{"key":"活力碘","value":0,"type":"supply"},{"key":"床罩","value":0,"type":"supply"},{"key":"医用面罩式雾化器","value":0,"type":"supply"},{"key":"测体温设备","value":0,"type":"supply"},{"key":"空气消毒设备","value":0,"type":"supply"},{"key":"医用紫外线消毒车","value":0,"type":"supply"},{"key":"官方链接","value":"https://www.dfmhp.com.cn/Html/News/Articles/1930.html","type":"url"},{"key":"医院地址","value":"湖北省十堰市张湾区大岭路16号","type":"address","coord":[0,0]},{"key":"联系人/联系方式","value":[{"name":"联系电话","tel":"0719-8272371"},{"name":"王老师","tel":"13972468860"}],"type":"contact"},{"key":"备注","value":"发布日期：2020年1月25日","type":"string"},{"key":"审核状态","value":"已审核","type":"enum"}],[{"key":"区县","value":"十堰市","type":"string"},{"key":"医院名称","value":"十堰市西苑医院","type":"string"},{"key":"普通医用口罩","value":1,"type":"supply","specification":"YY/T 0969-2013"},{"key":"医用外科口罩","value":1,"type":"supply","specification":"YY 0469-2010"},{"key":"医用防护口罩 | N95口罩","value":1,"type":"supply","specification":"GB 19083-2010, 建议3M 1860/1870/9123,防飞沫血液体液款"},{"key":"防冲击眼罩/护目镜/防护眼镜","value":1,"type":"supply"},{"key":"防护面罩","value":1,"type":"supply"},{"key":"防护帽/医用帽/圆帽","value":1,"type":"supply"},{"key":"隔离衣","value":0,"type":"supply"},{"key":"防护服","value":1,"type":"supply","specification":"GB 19082-2003"},{"key":"手术衣","value":1,"type":"supply"},{"key":"乳胶手套","value":0,"type":"supply","specification":"灭菌，GB 10213-2006"},{"key":"长筒胶鞋/防污染靴","value":0,"type":"supply"},{"key":"防污染鞋套","value":0,"type":"supply"},{"key":"防污染靴套","value":0,"type":"supply"},{"key":"84消毒液","value":0,"type":"supply"},{"key":"过氧乙酸","value":0,"type":"supply"},{"key":"75%酒精","value":0,"type":"supply"},{"key":"手部皮肤消毒液","value":0,"type":"supply"},{"key":"活力碘","value":0,"type":"supply"},{"key":"床罩","value":0,"type":"supply"},{"key":"医用面罩式雾化器","value":0,"type":"supply"},{"key":"测体温设备","value":0,"type":"supply"},{"key":"空气消毒设备","value":0,"type":"supply"},{"key":"医用紫外线消毒车","value":0,"type":"supply"},{"key":"官方链接","value":" https://wx1.sinaimg.cn/mw690/7c89135fly1gb9ul2r8h8j20io0pz797.jpg","type":"url"},{"key":"医院地址","value":"湖北省十堰市张湾区黄龙镇西城路271号","type":"address","coord":[0,0]},{"key":"联系人/联系方式","value":[{"name":"李主任","tel":"13872806221"},{"name":"陈主任","tel":"13986894949"}],"type":"contact"},{"key":"备注","value":"发布日期：2020年1月25日","type":"string"},{"key":"审核状态","value":"已审核","type":"enum"}],[{"key":"区县","value":"十堰市","type":"string"},{"key":"医院名称","value":"十堰市国药东风花果医院","type":"string"},{"key":"普通医用口罩","value":10000,"type":"supply","specification":"YY/T 0969-2013"},{"key":"医用外科口罩","value":4000,"type":"supply","specification":"YY 0469-2010"},{"key":"医用防护口罩 | N95口罩","value":8000,"type":"supply","specification":"GB 19083-2010, 建议3M 1860/1870/9123,防飞沫血液体液款"},{"key":"防冲击眼罩/护目镜/防护眼镜","value":1000,"type":"supply"},{"key":"防护面罩","value":0,"type":"supply"},{"key":"防护帽/医用帽/圆帽","value":4000,"type":"supply"},{"key":"隔离衣","value":3000,"type":"supply"},{"key":"防护服","value":1000,"type":"supply","specification":"GB 19082-2003"},{"key":"手术衣","value":0,"type":"supply"},{"key":"乳胶手套","value":4000,"type":"supply","specification":"灭菌，GB 10213-2006"},{"key":"长筒胶鞋/防污染靴","value":0,"type":"supply"},{"key":"防污染鞋套","value":4000,"type":"supply"},{"key":"防污染靴套","value":0,"type":"supply"},{"key":"84消毒液","value":0,"type":"supply"},{"key":"过氧乙酸","value":0,"type":"supply"},{"key":"75%酒精","value":0,"type":"supply"},{"key":"手部皮肤消毒液","value":0,"type":"supply"},{"key":"活力碘","value":0,"type":"supply"},{"key":"床罩","value":0,"type":"supply"},{"key":"医用面罩式雾化器","value":0,"type":"supply"},{"key":"测体温设备","value":0,"type":"supply"},{"key":"空气消毒设备","value":10,"type":"supply"},{"key":"医用紫外线消毒车","value":0,"type":"supply"},{"key":"官方链接","value":" https://wx3.sinaimg.cn/mw690/7c89135fly1gb9ukn78mmj20e90e176i.jpg","type":"url"},{"key":"医院地址","value":"湖北省十堰市张湾区新疆路39号","type":"address","coord":[0,0]},{"key":"联系人/联系方式","value":[{"name":"王伟","tel":"13886807577"}],"type":"contact"},{"key":"备注","value":"发布日期：2020年1月25日","type":"string"},{"key":"审核状态","value":"已审核","type":"enum"}],[{"key":"区县","value":"十堰市","type":"string"},{"key":"医院名称","value":"十堰市中医医院","type":"string"},{"key":"普通医用口罩","value":0,"type":"supply","specification":"YY/T 0969-2013"},{"key":"医用外科口罩","value":10000,"type":"supply","specification":"YY 0469-2010"},{"key":"医用防护口罩 | N95口罩","value":2000,"type":"supply","specification":"GB 19083-2010, 建议3M 1860/1870/9123,防飞沫血液体液款"},{"key":"防冲击眼罩/护目镜/防护眼镜","value":5000,"type":"supply"},{"key":"防护面罩","value":0,"type":"supply"},{"key":"防护帽/医用帽/圆帽","value":10000,"type":"supply"},{"key":"隔离衣","value":0,"type":"supply"},{"key":"防护服","value":5000,"type":"supply","specification":"GB 19082-2003"},{"key":"手术衣","value":0,"type":"supply"},{"key":"乳胶手套","value":5000,"type":"supply","specification":"灭菌，GB 10213-2006"},{"key":"长筒胶鞋/防污染靴","value":0,"type":"supply"},{"key":"防污染鞋套","value":0,"type":"supply"},{"key":"防污染靴套","value":0,"type":"supply"},{"key":"84消毒液","value":0,"type":"supply"},{"key":"过氧乙酸","value":0,"type":"supply"},{"key":"75%酒精","value":0,"type":"supply"},{"key":"手部皮肤消毒液","value":0,"type":"supply"},{"key":"活力碘","value":0,"type":"supply"},{"key":"床罩","value":0,"type":"supply"},{"key":"医用面罩式雾化器","value":0,"type":"supply"},{"key":"测体温设备","value":0,"type":"supply"},{"key":"空气消毒设备","value":0,"type":"supply"},{"key":"医用紫外线消毒车","value":0,"type":"supply"},{"key":"官方链接","value":" https://wx4.sinaimg.cn/mw690/7c89135fly1gb9ukq6gx5j20j609rjsj.jpg","type":"url"},{"key":"医院地址","value":"湖北省十堰市茅箭区丹江路1号","type":"address","coord":[0,0]},{"key":"联系人/联系方式","value":[{"name":"联系电话","tel":"0719-8792997"},{"name":"张老师","tel":"13636219299"}],"type":"contact"},{"key":"备注","value":"发布日期：2020年1月25日","type":"string"},{"key":"审核状态","value":"已审核","type":"enum"}],[{"key":"区县","value":"十堰市","type":"string"},{"key":"医院名称","value":"十堰市妇幼保健院","type":"string"},{"key":"普通医用口罩","value":1,"type":"supply","specification":"YY/T 0969-2013"},{"key":"医用外科口罩","value":1,"type":"supply","specification":"YY 0469-2010"},{"key":"医用防护口罩 | N95口罩","value":1,"type":"supply","specification":"GB 19083-2010, 建议3M 1860/1870/9123,防飞沫血液体液款"},{"key":"防冲击眼罩/护目镜/防护眼镜","value":1,"type":"supply"},{"key":"防护面罩","value":1,"type":"supply"},{"key":"防护帽/医用帽/圆帽","value":1,"type":"supply"},{"key":"隔离衣","value":0,"type":"supply"},{"key":"防护服","value":1,"type":"supply","specification":"GB 19082-2003"},{"key":"手术衣","value":1,"type":"supply"},{"key":"乳胶手套","value":0,"type":"supply","specification":"灭菌，GB 10213-2006"},{"key":"长筒胶鞋/防污染靴","value":0,"type":"supply"},{"key":"防污染鞋套","value":0,"type":"supply"},{"key":"防污染靴套","value":0,"type":"supply"},{"key":"84消毒液","value":0,"type":"supply"},{"key":"过氧乙酸","value":0,"type":"supply"},{"key":"75%酒精","value":0,"type":"supply"},{"key":"手部皮肤消毒液","value":0,"type":"supply"},{"key":"活力碘","value":0,"type":"supply"},{"key":"床罩","value":0,"type":"supply"},{"key":"医用面罩式雾化器","value":0,"type":"supply"},{"key":"测体温设备","value":0,"type":"supply"},{"key":"空气消毒设备","value":0,"type":"supply"},{"key":"医用紫外线消毒车","value":0,"type":"supply"},{"key":"官方链接","value":" https://wx4.sinaimg.cn/mw690/7c89135fly1gb9ul9jtoej20j60ten66.jpg","type":"url"},{"key":"医院地址","value":"湖北省十堰市人民北路62号妇幼保健院总务科","type":"address","coord":[0,0]},{"key":"联系人/联系方式","value":[{"name":"胡民","tel":"13508682859"}],"type":"contact"},{"key":"备注","value":"发布日期：2020年1月25日","type":"string"},{"key":"审核状态","value":"已审核","type":"enum"}],[{"key":"区县","value":"十堰市","type":"string"},{"key":"医院名称","value":"十堰市太和医院","type":"string"},{"key":"普通医用口罩","value":1,"type":"supply","specification":"YY/T 0969-2013"},{"key":"医用外科口罩","value":1,"type":"supply","specification":"YY 0469-2010"},{"key":"医用防护口罩 | N95口罩","value":1,"type":"supply","specification":"GB 19083-2010, 建议3M 1860/1870/9123,防飞沫血液体液款"},{"key":"防冲击眼罩/护目镜/防护眼镜","value":1,"type":"supply"},{"key":"防护面罩","value":1,"type":"supply"},{"key":"防护帽/医用帽/圆帽","value":1,"type":"supply"},{"key":"隔离衣","value":0,"type":"supply"},{"key":"防护服","value":1,"type":"supply","specification":"GB 19082-2003"},{"key":"手术衣","value":1,"type":"supply"},{"key":"乳胶手套","value":1,"type":"supply","specification":"灭菌，GB 10213-2006"},{"key":"长筒胶鞋/防污染靴","value":0,"type":"supply"},{"key":"防污染鞋套","value":0,"type":"supply"},{"key":"防污染靴套","value":0,"type":"supply"},{"key":"84消毒液","value":0,"type":"supply"},{"key":"过氧乙酸","value":0,"type":"supply"},{"key":"75%酒精","value":0,"type":"supply"},{"key":"手部皮肤消毒液","value":0,"type":"supply"},{"key":"活力碘","value":0,"type":"supply"},{"key":"床罩","value":0,"type":"supply"},{"key":"医用面罩式雾化器","value":0,"type":"supply"},{"key":"测体温设备","value":0,"type":"supply"},{"key":"空气消毒设备","value":0,"type":"supply"},{"key":"医用紫外线消毒车","value":0,"type":"supply"},{"key":"官方链接","value":" https://wx4.sinaimg.cn/mw690/7c89135fly1gb9ul4xnfsj20j60pkq7c.jpg","type":"url"},{"key":"医院地址","value":"湖北省十堰市茅箭区人民南路32号","type":"address","coord":[0,0]},{"key":"联系人/联系方式","value":[{"name":"李女士","tel":"18772243386"},{"name":"王女士","tel":"13797865731"},{"name":"刘女士","tel":"13635718126"}],"type":"contact"},{"key":"备注","value":"发布日期：2020年1月25日","type":"string"},{"key":"审核状态","value":"已审核","type":"enum"}],[{"key":"区县","value":"十堰市","type":"string"},{"key":"医院名称","value":"十堰市国药东风茅箭医院","type":"string"},{"key":"普通医用口罩","value":0,"type":"supply","specification":"YY/T 0969-2013"},{"key":"医用外科口罩","value":1,"type":"supply","specification":"YY 0469-2010"},{"key":"医用防护口罩 | N95口罩","value":1,"type":"supply","specification":"GB 19083-2010, 建议3M 1860/1870/9123,防飞沫血液体液款"},{"key":"防冲击眼罩/护目镜/防护眼镜","value":1,"type":"supply"},{"key":"防护面罩","value":1,"type":"supply"},{"key":"防护帽/医用帽/圆帽","value":1,"type":"supply"},{"key":"隔离衣","value":1,"type":"supply"},{"key":"防护服","value":1,"type":"supply","specification":"GB 19082-2003"},{"key":"手术衣","value":1,"type":"supply"},{"key":"乳胶手套","value":1,"type":"supply","specification":"灭菌，GB 10213-2006"},{"key":"长筒胶鞋/防污染靴","value":0,"type":"supply"},{"key":"防污染鞋套","value":0,"type":"supply"},{"key":"防污染靴套","value":0,"type":"supply"},{"key":"84消毒液","value":0,"type":"supply"},{"key":"过氧乙酸","value":0,"type":"supply"},{"key":"75%酒精","value":0,"type":"supply"},{"key":"手部皮肤消毒液","value":0,"type":"supply"},{"key":"活力碘","value":0,"type":"supply"},{"key":"床罩","value":0,"type":"supply"},{"key":"医用面罩式雾化器","value":0,"type":"supply"},{"key":"测体温设备","value":0,"type":"supply"},{"key":"空气消毒设备","value":0,"type":"supply"},{"key":"医用紫外线消毒车","value":0,"type":"supply"},{"key":"官方链接","value":" https://wx3.sinaimg.cn/mw690/7c89135fly1gb9ul7b4auj20j60y278h.jpg","type":"url"},{"key":"医院地址","value":"湖北省十堰市茅箭区东风大道12号","type":"address","coord":[0,0]},{"key":"联系人/联系方式","value":[{"name":"郭先生","tel":"13135710210"}],"type":"contact"},{"key":"备注","value":"发布日期：2020年1月26日","type":"string"},{"key":"审核状态","value":"已审核","type":"enum"}],[{"key":"区县","value":"丹江口市","type":"string"},{"key":"医院名称","value":"丹江口市第一医院","type":"string"},{"key":"普通医用口罩","value":1,"type":"supply","specification":"YY/T 0969-2013"},{"key":"医用外科口罩","value":0,"type":"supply","specification":"YY 0469-2010"},{"key":"医用防护口罩 | N95口罩","value":1,"type":"supply","specification":"GB 19083-2010, 建议3M 1860/1870/9123,防飞沫血液体液款"},{"key":"防冲击眼罩/护目镜/防护眼镜","value":1,"type":"supply"},{"key":"防护面罩","value":1,"type":"supply"},{"key":"防护帽/医用帽/圆帽","value":0,"type":"supply"},{"key":"隔离衣","value":0,"type":"supply"},{"key":"防护服","value":1,"type":"supply","specification":"GB 19082-2003"},{"key":"手术衣","value":1,"type":"supply"},{"key":"乳胶手套","value":1,"type":"supply","specification":"灭菌，GB 10213-2006"},{"key":"长筒胶鞋/防污染靴","value":0,"type":"supply"},{"key":"防污染鞋套","value":0,"type":"supply"},{"key":"防污染靴套","value":0,"type":"supply"},{"key":"84消毒液","value":0,"type":"supply"},{"key":"过氧乙酸","value":0,"type":"supply"},{"key":"75%酒精","value":0,"type":"supply"},{"key":"手部皮肤消毒液","value":0,"type":"supply"},{"key":"活力碘","value":0,"type":"supply"},{"key":"床罩","value":0,"type":"supply"},{"key":"医用面罩式雾化器","value":0,"type":"supply"},{"key":"测体温设备","value":0,"type":"supply"},{"key":"空气消毒设备","value":0,"type":"supply"},{"key":"医用紫外线消毒车","value":0,"type":"supply"},{"key":"官方链接","value":" https://wx1.sinaimg.cn/mw690/7c89135fly1gb9ulj2kwzj20fk0m8jts.jpg","type":"url"},{"key":"医院地址","value":"湖北省十堰市丹江口市沙陀营路32号","type":"address","coord":[0,0]},{"key":"联系人/联系方式","value":[{"name":"包海","tel":"18007281603"}],"type":"contact"},{"key":"备注","value":"发布日期：2020年1月25日","type":"string"},{"key":"审核状态","value":"已审核","type":"enum"}],[{"key":"区县","value":"丹江口市","type":"string"},{"key":"医院名称","value":"十堰市铁路医院","type":"string"},{"key":"普通医用口罩","value":0,"type":"supply","specification":"YY/T 0969-2013"},{"key":"医用外科口罩","value":10000,"type":"supply","specification":"YY 0469-2010"},{"key":"医用防护口罩 | N95口罩","value":2000,"type":"supply","specification":"GB 19083-2010, 建议3M 1860/1870/9123,防飞沫血液体液款"},{"key":"防冲击眼罩/护目镜/防护眼镜","value":1000,"type":"supply"},{"key":"防护面罩","value":500,"type":"supply"},{"key":"防护帽/医用帽/圆帽","value":0,"type":"supply"},{"key":"隔离衣","value":500,"type":"supply"},{"key":"防护服","value":1000,"type":"supply","specification":"GB 19082-2003"},{"key":"手术衣","value":100,"type":"supply"},{"key":"乳胶手套","value":1000,"type":"supply","specification":"灭菌，GB 10213-2006"},{"key":"长筒胶鞋/防污染靴","value":0,"type":"supply"},{"key":"防污染鞋套","value":1000,"type":"supply"},{"key":"防污染靴套","value":0,"type":"supply"},{"key":"84消毒液","value":500,"type":"supply"},{"key":"过氧乙酸","value":500,"type":"supply"},{"key":"75%酒精","value":200,"type":"supply"},{"key":"手部皮肤消毒液","value":200,"type":"supply"},{"key":"活力碘","value":0,"type":"supply"},{"key":"床罩","value":0,"type":"supply"},{"key":"医用面罩式雾化器","value":0,"type":"supply"},{"key":"测体温设备","value":0,"type":"supply"},{"key":"空气消毒设备","value":0,"type":"supply"},{"key":"医用紫外线消毒车","value":0,"type":"supply"},{"key":"官方链接","value":" https://wx1.sinaimg.cn/mw690/7c89135fly1gb9ukf8wvbj20fr0c2acj.jpg","type":"url"},{"key":"医院地址","value":"湖北省十堰市丹江口市六里坪镇大柳树","type":"address","coord":[0,0]},{"key":"联系人/联系方式","value":[{"name":"吴廷臣","tel":"13597908216"}],"type":"contact"},{"key":"备注","value":"人血丙种球蛋白，肌注用10%3ml(300mg):50瓶\n发布日期：2020年1月25日","type":"string"},{"key":"审核状态","value":"已审核","type":"enum"}],[{"key":"区县","value":"竹山县","type":"string"},{"key":"医院名称","value":"竹山县人民医院","type":"string"},{"key":"普通医用口罩","value":1,"type":"supply","specification":"YY/T 0969-2013"},{"key":"医用外科口罩","value":1,"type":"supply","specification":"YY 0469-2010"},{"key":"医用防护口罩 | N95口罩","value":1,"type":"supply","specification":"GB 19083-2010, 建议3M 1860/1870/9123,防飞沫血液体液款"},{"key":"防冲击眼罩/护目镜/防护眼镜","value":1,"type":"supply"},{"key":"防护面罩","value":1,"type":"supply"},{"key":"防护帽/医用帽/圆帽","value":1,"type":"supply"},{"key":"隔离衣","value":0,"type":"supply"},{"key":"防护服","value":1,"type":"supply","specification":"GB 19082-2003"},{"key":"手术衣","value":0,"type":"supply"},{"key":"乳胶手套","value":1,"type":"supply","specification":"灭菌，GB 10213-2006"},{"key":"长筒胶鞋/防污染靴","value":0,"type":"supply"},{"key":"防污染鞋套","value":0,"type":"supply"},{"key":"防污染靴套","value":0,"type":"supply"},{"key":"84消毒液","value":0,"type":"supply"},{"key":"过氧乙酸","value":0,"type":"supply"},{"key":"75%酒精","value":0,"type":"supply"},{"key":"手部皮肤消毒液","value":0,"type":"supply"},{"key":"活力碘","value":0,"type":"supply"},{"key":"床罩","value":0,"type":"supply"},{"key":"医用面罩式雾化器","value":0,"type":"supply"},{"key":"测体温设备","value":0,"type":"supply"},{"key":"空气消毒设备","value":0,"type":"supply"},{"key":"医用紫外线消毒车","value":0,"type":"supply"},{"key":"官方链接","value":" https://wx3.sinaimg.cn/mw690/7c89135fly1gb9ulftuzaj20j617179t.jpg","type":"url"},{"key":"医院地址","value":"湖北省十堰市竹山县城关镇人民路3号","type":"address","coord":[0,0]},{"key":"联系人/联系方式","value":[{"name":"喻艳","tel":"15872727077"}],"type":"contact"},{"key":"备注","value":"发布日期：2020年1月25日","type":"string"},{"key":"审核状态","value":"已审核","type":"enum"}],[{"key":"区县","value":"十堰市","type":"string"},{"key":"医院名称","value":"十堰市红十字会","type":"string"},{"key":"普通医用口罩","value":1,"type":"supply","specification":"YY/T 0969-2013"},{"key":"医用外科口罩","value":1,"type":"supply","specification":"YY 0469-2010"},{"key":"医用防护口罩 | N95口罩","value":1,"type":"supply","specification":"GB 19083-2010, 建议3M 1860/1870/9123,防飞沫血液体液款"},{"key":"防冲击眼罩/护目镜/防护眼镜","value":1,"type":"supply"},{"key":"防护面罩","value":1,"type":"supply"},{"key":"防护帽/医用帽/圆帽","value":1,"type":"supply"},{"key":"隔离衣","value":1,"type":"supply"},{"key":"防护服","value":1,"type":"supply","specification":"GB 19082-2003"},{"key":"手术衣","value":1,"type":"supply"},{"key":"乳胶手套","value":1,"type":"supply","specification":"灭菌，GB 10213-2006"},{"key":"长筒胶鞋/防污染靴","value":1,"type":"supply"},{"key":"防污染鞋套","value":1,"type":"supply"},{"key":"防污染靴套","value":1,"type":"supply"},{"key":"84消毒液","value":1,"type":"supply"},{"key":"过氧乙酸","value":1,"type":"supply"},{"key":"75%酒精","value":1,"type":"supply"},{"key":"手部皮肤消毒液","value":1,"type":"supply"},{"key":"活力碘","value":1,"type":"supply"},{"key":"床罩","value":1,"type":"supply"},{"key":"医用面罩式雾化器","value":1,"type":"supply"},{"key":"测体温设备","value":1,"type":"supply"},{"key":"空气消毒设备","value":1,"type":"supply"},{"key":"医用紫外线消毒车","value":1,"type":"supply"},{"key":"官方链接","value":"http://www.shiyan.gov.cn/xwzx_2477/syyw_2479/202001/t20200125_2004289.shtml","type":"url"},{"key":"医院地址","value":"湖北省十堰市茅箭区柳林路25号","type":"address","coord":[0,0]},{"key":"联系人/联系方式","value":[{"name":"联系电话","tel":"0719-8682758"},{"name":"魏源源","tel":"18942182731"},{"name":"吴远海","tel":"15871126868"}],"type":"contact"},{"key":"备注","value":"接受捐赠账户名：十堰市红十字会；\n捐赠账号：415010100100202914；\n开户行：兴业银行十堰分行；\n口罩需求量大，暂不接受与疫情防控无关的物资和境外捐赠。","type":"string"},{"key":"审核状态","value":"已审核","type":"enum"}],[{"key":"区县","value":"十堰市","type":"string"},{"key":"医院名称","value":"十堰市慈善总会","type":"string"},{"key":"普通医用口罩","value":1,"type":"supply","specification":"YY/T 0969-2013"},{"key":"医用外科口罩","value":1,"type":"supply","specification":"YY 0469-2010"},{"key":"医用防护口罩 | N95口罩","value":1,"type":"supply","specification":"GB 19083-2010, 建议3M 1860/1870/9123,防飞沫血液体液款"},{"key":"防冲击眼罩/护目镜/防护眼镜","value":1,"type":"supply"},{"key":"防护面罩","value":1,"type":"supply"},{"key":"防护帽/医用帽/圆帽","value":1,"type":"supply"},{"key":"隔离衣","value":1,"type":"supply"},{"key":"防护服","value":1,"type":"supply","specification":"GB 19082-2003"},{"key":"手术衣","value":1,"type":"supply"},{"key":"乳胶手套","value":1,"type":"supply","specification":"灭菌，GB 10213-2006"},{"key":"长筒胶鞋/防污染靴","value":1,"type":"supply"},{"key":"防污染鞋套","value":1,"type":"supply"},{"key":"防污染靴套","value":1,"type":"supply"},{"key":"84消毒液","value":1,"type":"supply"},{"key":"过氧乙酸","value":1,"type":"supply"},{"key":"75%酒精","value":1,"type":"supply"},{"key":"手部皮肤消毒液","value":1,"type":"supply"},{"key":"活力碘","value":1,"type":"supply"},{"key":"床罩","value":1,"type":"supply"},{"key":"医用面罩式雾化器","value":1,"type":"supply"},{"key":"测体温设备","value":1,"type":"supply"},{"key":"空气消毒设备","value":1,"type":"supply"},{"key":"医用紫外线消毒车","value":1,"type":"supply"},{"key":"官方链接","value":"http://www.shiyan.gov.cn/xwzx_2477/syyw_2479/202001/t20200126_2004325.shtml","type":"url"},{"key":"医院地址","value":"湖北省十堰市茅箭区朝阳中路31号民政局5楼","type":"address","coord":[0,0]},{"key":"联系人/联系方式","value":[{"name":"联系电话","tel":"0719-8117112"},{"name":"王紫焱","tel":"13636239923"},{"name":"冯筱莹","tel":"19986480718"}],"type":"contact"},{"key":"备注","value":"接受捐赠户名：十堰市慈善总会；\n账号：42001616008053003870；\n开户行：建设银行十堰五堰支行；\n口罩需求量大。","type":"string"},{"key":"审核状态","value":"已审核","type":"enum"}]]