[{"id":0,"province":"湖北","city":"仙桃市","district":"仙桃市","name":"仙桃市第一人民医院","supplies":[{"key":"普通医用口罩","value":1,"specification":"YY/T 0969-2013"},{"key":"医用防护口罩 | N95口罩","value":1,"specification":"GB 19083-2010, 建议3M 1860/1870/9123,防飞沫血液体液款"},{"key":"防冲击眼罩/护目镜/防护眼镜","value":1},{"key":"防护面罩","value":1},{"key":"防护帽/医用帽/圆帽","value":1},{"key":"防护服","value":1,"specification":"GB 19082-2003"},{"key":"手术衣","value":1}],"address":"湖北省仙桃市沔州大道中段29号物资供应科","url":" https://mmbiz.qpic.cn/mmbiz_png/kuXibx7G0FwEZcQGtgxo8icNUU5smZPftsjkxcBj1tktr2jwJPSMIYMTtbJKfnsG646DugJpziasy0a4LWtic6tcvg/640?wx_fmt=png&tp=webp&wxfrom=5&wx_lazy=1&wx_co=1","remark":"发布日期：2020年1月24日","contacts":[{"name":"关键","tel":"13707223566"},{"name":"彭铁军","tel":"13593918277"}]},{"id":1,"province":"湖北","city":"仙桃市","district":"仙桃市","name":"仙桃市红十字会","supplies":[{"key":"普通医用口罩","value":1,"specification":"YY/T 0969-2013"},{"key":"医用外科口罩","value":1,"specification":"YY 0469-2010"},{"key":"医用防护口罩 | N95口罩","value":1,"specification":"GB 19083-2010, 建议3M 1860/1870/9123,防飞沫血液体液款"},{"key":"防冲击眼罩/护目镜/防护眼镜","value":1},{"key":"防护面罩","value":1},{"key":"防护帽/医用帽/圆帽","value":1},{"key":"隔离衣","value":1},{"key":"防护服","value":1,"specification":"GB 19082-2003"},{"key":"手术衣","value":1},{"key":"乳胶手套","value":1,"specification":"灭菌，GB 10213-2006"},{"key":"长筒胶鞋/防污染靴","value":1},{"key":"防污染鞋套","value":1},{"key":"防污染靴套","value":1},{"key":"84消毒液","value":1},{"key":"过氧乙酸","value":1},{"key":"75%酒精","value":1},{"key":"手部皮肤消毒液","value":1},{"key":"活力碘","value":1},{"key":"床罩","value":1},{"key":"医用面罩式雾化器","value":1},{"key":"测体温设备","value":1},{"key":"空气消毒设备","value":1},{"key":"医用紫外线消毒车","value":1}],"address":"湖北省仙桃市沔阳大道18号","url":" http://www.xiantao.gov.cn/zwgk/gsgg/202001/t20200128_360177.shtml","remark":"户名：仙桃市红十字会办公室\n帐号：4200 1627 4360 5300 1558\n开户行：建设银行仙桃支行","contacts":[{"name":"联系电话","tel":"0728-3223737"},{"name":"阮小俊","tel":"18007229992"}]}]